{"hours": [9, 11, 13, 15], "deploys": ["dual", "single"], "altitudes": [1000, 3200, 5500, 7800, 10000], "site_px": [1693.0, 1693.0], "image_view_box": [0, 0, 3386, 3386], "wide_view_box": [-2579.3, -2579.3, 8544.6, 8544.6], "ft_to_px_scale": {"x": 0.296699, "y": 0.296699}, "boost_angle_deg": 10, "data": {"9_dual": [{"altitude": 1000, "core_hull_px": [[1672.2, 1352.1], [1682.7, 1517.9], [1721.0, 1509.2], [1800.4, 1444.1], [1903.3, 1205.5], [1867.3, 1214.2], [1757.3, 1246.9], [1717.9, 1276.9]], "buffer_hull_px": [[1619.9, 1352.1], [1630.4, 1517.9], [1637.4, 1544.0], [1656.6, 1563.2], [1682.7, 1570.2], [1721.0, 1561.5], [1747.1, 1554.5], [1826.6, 1489.4], [1845.7, 1470.2], [1948.6, 1231.6], [1955.6, 1205.5], [1948.6, 1179.3], [1929.5, 1160.2], [1903.3, 1153.2], [1867.3, 1161.9], [1841.2, 1168.9], [1731.1, 1201.6], [1691.8, 1231.6], [1672.6, 1250.7], [1626.9, 1326.0]], "buffer_radius_ft": 176.3, "points": [{"model": "gfs", "rate": "slow", "x_ft": 216.7, "y_ft": 1503.6, "px": 1757.3, "py": 1246.9}, {"model": "gfs", "rate": "fast", "x_ft": 111.4, "y_ft": 768.1, "px": 1726.0, "py": 1465.1}, {"model": "hrrr", "rate": "slow", "x_ft": 708.9, "y_ft": 1643.2, "px": 1903.3, "py": 1205.5}, {"model": "hrrr", "rate": "fast", "x_ft": 362.1, "y_ft": 839.1, "px": 1800.4, "py": 1444.1}, {"model": "ecmwf", "rate": "slow", "x_ft": 184.8, "y_ft": 1215.5, "px": 1747.8, "py": 1332.4}, {"model": "ecmwf", "rate": "fast", "x_ft": 94.3, "y_ft": 619.6, "px": 1721.0, "py": 1509.2}, {"model": "icon", "rate": "slow", "x_ft": 84.0, "y_ft": 1402.5, "px": 1717.9, "py": 1276.9}, {"model": "icon", "rate": "fast", "x_ft": 44.2, "y_ft": 716.7, "px": 1706.1, "py": 1480.4}, {"model": "arpege", "rate": "slow", "x_ft": -70.2, "y_ft": 1148.9, "px": 1672.2, "py": 1352.1}, {"model": "arpege", "rate": "fast", "x_ft": -34.7, "y_ft": 590.2, "px": 1682.7, "py": 1517.9}, {"model": "gem", "rate": "slow", "x_ft": 587.6, "y_ft": 1613.7, "px": 1867.3, "py": 1214.2}, {"model": "gem", "rate": "fast", "x_ft": 300.4, "y_ft": 823.9, "px": 1782.1, "py": 1448.5}]}, {"altitude": 3200, "core_hull_px": [[2019.2, 954.0], [1826.9, 1008.6], [1753.8, 1060.7], [1745.0, 1388.6], [1893.2, 1242.9]], "buffer_hull_px": [[2103.0, 809.0], [2019.2, 786.6], [1935.5, 809.0], [1743.2, 863.6], [1670.0, 915.7], [1608.8, 977.0], [1586.3, 1060.7], [1577.6, 1388.6], [1600.0, 1472.3], [1661.3, 1533.6], [1745.0, 1556.0], [1828.7, 1533.6], [1976.9, 1387.8], [2038.2, 1326.6], [2164.2, 1037.7], [2186.7, 954.0], [2164.2, 870.3]], "buffer_radius_ft": 564.2, "points": [{"model": "gfs", "rate": "slow", "x_ft": 451.3, "y_ft": 2306.7, "px": 1826.9, "py": 1008.6}, {"model": "gfs", "rate": "fast", "x_ft": 299.1, "y_ft": 1410.6, "px": 1781.7, "py": 1274.5}, {"model": "hrrr", "rate": "slow", "x_ft": 1099.6, "y_ft": 2490.8, "px": 2019.2, "py": 954.0}, {"model": "hrrr", "rate": "fast", "x_ft": 674.7, "y_ft": 1517.2, "px": 1893.2, "py": 1242.9}, {"model": "ecmwf", "rate": "slow", "x_ft": 285.9, "y_ft": 1723.4, "px": 1777.8, "py": 1181.7}, {"model": "ecmwf", "rate": "fast", "x_ft": 175.2, "y_ft": 1025.9, "px": 1745.0, "py": 1388.6}, {"model": "icon", "rate": "slow", "x_ft": 365.0, "y_ft": 2164.9, "px": 1801.3, "py": 1050.7}, {"model": "icon", "rate": "fast", "x_ft": 269.0, "y_ft": 1326.7, "px": 1772.8, "py": 1299.4}, {"model": "arpege", "rate": "slow", "x_ft": 204.8, "y_ft": 2131.2, "px": 1753.8, "py": 1060.7}, {"model": "arpege", "rate": "fast", "x_ft": 185.3, "y_ft": 1376.0, "px": 1748.0, "py": 1284.7}, {"model": "gem", "rate": "slow", "x_ft": 948.6, "y_ft": 2437.7, "px": 1974.4, "py": 969.7}, {"model": "gem", "rate": "fast", "x_ft": 589.2, "y_ft": 1483.1, "px": 1867.8, "py": 1253.0}]}, {"altitude": 5500, "core_hull_px": [[2160.1, 686.2], [2096.8, 670.2], [1898.6, 704.2], [1829.8, 982.9], [1786.6, 1229.6], [2005.9, 1028.7]], "buffer_hull_px": [[1542.1, 982.9], [1498.8, 1229.6], [1537.4, 1373.5], [1642.7, 1478.8], [1786.6, 1517.4], [1930.4, 1478.8], [2149.7, 1277.8], [2255.0, 1172.5], [2409.3, 830.1], [2447.8, 686.2], [2409.3, 542.4], [2304.0, 437.0], [2160.1, 398.5], [2096.8, 382.4], [1898.6, 416.5], [1754.7, 455.0], [1649.4, 560.3], [1610.8, 704.2]], "buffer_radius_ft": 969.8, "points": [{"model": "gfs", "rate": "slow", "x_ft": 702.7, "y_ft": 3168.2, "px": 1901.5, "py": 753.0}, {"model": "gfs", "rate": "fast", "x_ft": 500.2, "y_ft": 2099.8, "px": 1841.4, "py": 1070.0}, {"model": "hrrr", "rate": "slow", "x_ft": 1574.3, "y_ft": 3393.3, "px": 2160.1, "py": 686.2}, {"model": "hrrr", "rate": "fast", "x_ft": 1054.5, "y_ft": 2239.1, "px": 2005.9, "py": 1028.7}, {"model": "ecmwf", "rate": "slow", "x_ft": 461.1, "y_ft": 2393.2, "px": 1829.8, "py": 982.9}, {"model": "ecmwf", "rate": "fast", "x_ft": 315.4, "y_ft": 1561.8, "px": 1786.6, "py": 1229.6}, {"model": "icon", "rate": "slow", "x_ft": 874.0, "y_ft": 3045.5, "px": 1952.3, "py": 789.4}, {"model": "icon", "rate": "fast", "x_ft": 676.2, "y_ft": 2031.1, "px": 1893.6, "py": 1090.4}, {"model": "arpege", "rate": "slow", "x_ft": 692.9, "y_ft": 3332.6, "px": 1898.6, "py": 704.2}, {"model": "arpege", "rate": "fast", "x_ft": 575.7, "y_ft": 2337.2, "px": 1863.8, "py": 999.6}, {"model": "gem", "rate": "slow", "x_ft": 1360.8, "y_ft": 3447.3, "px": 2096.8, "py": 670.2}, {"model": "gem", "rate": "fast", "x_ft": 919.0, "y_ft": 2290.8, "px": 1965.7, "py": 1013.3}]}, {"altitude": 7800, "core_hull_px": [[2288.8, 434.7], [2221.4, 355.6], [2031.7, 365.5], [1955.0, 509.9], [1908.0, 744.2], [1849.1, 1038.6], [2108.8, 827.4]], "buffer_hull_px": [[1678.3, 161.5], [1601.7, 305.8], [1547.0, 509.9], [1499.9, 744.2], [1441.0, 1038.6], [1495.7, 1242.7], [1645.1, 1392.0], [1849.1, 1446.7], [2053.1, 1392.0], [2312.8, 1180.8], [2462.2, 1031.5], [2642.2, 638.7], [2696.8, 434.7], [2642.2, 230.7], [2574.8, 151.6], [2425.4, 2.2], [2221.4, -52.5], [2031.7, -42.5], [1827.6, 12.1]], "buffer_radius_ft": 1375.4, "points": [{"model": "gfs", "rate": "slow", "x_ft": 883.2, "y_ft": 3987.6, "px": 1955.0, "py": 509.9}, {"model": "gfs", "rate": "fast", "x_ft": 644.6, "y_ft": 2755.3, "px": 1884.2, "py": 875.5}, {"model": "hrrr", "rate": "slow", "x_ft": 2008.0, "y_ft": 4241.0, "px": 2288.8, "py": 434.7}, {"model": "hrrr", "rate": "fast", "x_ft": 1401.4, "y_ft": 2917.3, "px": 2108.8, "py": 827.4}, {"model": "ecmwf", "rate": "slow", "x_ft": 724.5, "y_ft": 3197.8, "px": 1908.0, "py": 744.2}, {"model": "ecmwf", "rate": "fast", "x_ft": 526.2, "y_ft": 2205.5, "px": 1849.1, "py": 1038.6}, {"model": "icon", "rate": "slow", "x_ft": 1415.8, "y_ft": 3935.1, "px": 2113.1, "py": 525.5}, {"model": "icon", "rate": "fast", "x_ft": 1109.6, "y_ft": 2742.8, "px": 2022.2, "py": 879.2}, {"model": "arpege", "rate": "slow", "x_ft": 1141.5, "y_ft": 4474.2, "px": 2031.7, "py": 365.5}, {"model": "arpege", "rate": "fast", "x_ft": 934.6, "y_ft": 3250.4, "px": 1970.3, "py": 728.6}, {"model": "gem", "rate": "slow", "x_ft": 1780.9, "y_ft": 4507.6, "px": 2221.4, "py": 355.6}, {"model": "gem", "rate": "fast", "x_ft": 1255.0, "y_ft": 3139.0, "px": 2065.4, "py": 761.7}]}, {"altitude": 10000, "core_hull_px": [[1915.9, 672.4], [1930.7, 829.5], [2185.1, 623.8], [2384.2, 180.2], [2365.0, 51.1], [2128.0, 71.9], [1994.6, 256.0]], "buffer_hull_px": [[1392.8, 672.4], [1407.5, 829.5], [1477.6, 1091.1], [1669.1, 1282.5], [1930.7, 1352.6], [2192.3, 1282.5], [2446.7, 1076.9], [2638.2, 885.4], [2837.3, 441.7], [2907.3, 180.2], [2888.2, 51.1], [2818.1, -210.5], [2626.6, -402.0], [2365.0, -472.1], [2128.0, -451.2], [1866.4, -381.1], [1674.9, -189.6], [1541.6, -5.6], [1471.5, 256.0]], "buffer_radius_ft": 1763.3, "points": [{"model": "gfs", "rate": "slow", "x_ft": 1016.7, "y_ft": 4843.5, "px": 1994.6, "py": 256.0}, {"model": "gfs", "rate": "fast", "x_ft": 751.4, "y_ft": 3440.0, "px": 1915.9, "py": 672.4}, {"model": "hrrr", "rate": "slow", "x_ft": 2329.6, "y_ft": 5098.9, "px": 2384.2, "py": 180.2}, {"model": "hrrr", "rate": "fast", "x_ft": 1658.7, "y_ft": 3603.7, "px": 2185.1, "py": 623.8}, {"model": "ecmwf", "rate": "slow", "x_ft": 1068.3, "y_ft": 4079.0, "px": 2010.0, "py": 482.8}, {"model": "ecmwf", "rate": "fast", "x_ft": 801.2, "y_ft": 2910.4, "px": 1930.7, "py": 829.5}, {"model": "icon", "rate": "slow", "x_ft": 1839.4, "y_ft": 4829.4, "px": 2238.8, "py": 260.1}, {"model": "icon", "rate": "fast", "x_ft": 1448.5, "y_ft": 3458.2, "px": 2122.8, "py": 666.9}, {"model": "arpege", "rate": "slow", "x_ft": 1466.2, "y_ft": 5463.7, "px": 2128.0, "py": 71.9}, {"model": "arpege", "rate": "fast", "x_ft": 1194.4, "y_ft": 4042.0, "px": 2047.4, "py": 493.7}, {"model": "gem", "rate": "slow", "x_ft": 2265.1, "y_ft": 5533.9, "px": 2365.0, "py": 51.1}, {"model": "gem", "rate": "fast", "x_ft": 1642.4, "y_ft": 3960.1, "px": 2180.3, "py": 518.1}]}], "9_single": [{"altitude": 1000, "core_hull_px": [[1674.9, 1242.9], [1683.9, 1468.0], [1727.2, 1471.6], [1824.7, 1388.8], [1956.4, 1084.5], [1912.9, 1096.0], [1778.2, 1134.0], [1733.0, 1169.7]], "buffer_hull_px": [[1622.6, 1242.9], [1631.6, 1468.0], [1638.6, 1494.1], [1657.8, 1513.3], [1683.9, 1520.3], [1727.2, 1523.9], [1753.3, 1516.9], [1850.9, 1434.1], [1870.0, 1414.9], [2001.7, 1110.7], [2008.7, 1084.5], [2001.7, 1058.3], [1982.6, 1039.2], [1956.4, 1032.2], [1912.9, 1043.7], [1886.8, 1050.7], [1752.1, 1088.7], [1706.9, 1124.4], [1687.7, 1143.5], [1629.6, 1216.8]], "buffer_radius_ft": 176.3, "points": [{"model": "gfs", "rate": "10fps", "x_ft": 287.3, "y_ft": 1884.1, "px": 1778.2, "py": 1134.0}, {"model": "gfs", "rate": "20fps", "x_ft": 143.6, "y_ft": 942.1, "px": 1735.6, "py": 1413.5}, {"model": "hrrr", "rate": "10fps", "x_ft": 887.8, "y_ft": 2050.9, "px": 1956.4, "py": 1084.5}, {"model": "hrrr", "rate": "20fps", "x_ft": 443.9, "y_ft": 1025.4, "px": 1824.7, "py": 1388.8}, {"model": "ecmwf", "rate": "10fps", "x_ft": 230.4, "y_ft": 1492.3, "px": 1761.4, "py": 1250.2}, {"model": "ecmwf", "rate": "20fps", "x_ft": 115.2, "y_ft": 746.2, "px": 1727.2, "py": 1471.6}, {"model": "icon", "rate": "10fps", "x_ft": 134.9, "y_ft": 1763.8, "px": 1733.0, "py": 1169.7}, {"model": "icon", "rate": "20fps", "x_ft": 67.5, "y_ft": 881.9, "px": 1713.0, "py": 1431.3}, {"model": "arpege", "rate": "10fps", "x_ft": -61.0, "y_ft": 1516.9, "px": 1674.9, "py": 1242.9}, {"model": "arpege", "rate": "20fps", "x_ft": -30.5, "y_ft": 758.4, "px": 1683.9, "py": 1468.0}, {"model": "gem", "rate": "10fps", "x_ft": 741.2, "y_ft": 2012.2, "px": 1912.9, "py": 1096.0}, {"model": "gem", "rate": "20fps", "x_ft": 370.6, "y_ft": 1006.1, "px": 1803.0, "py": 1394.5}]}, {"altitude": 3200, "core_hull_px": [[2883.8, -927.4], [2327.4, -1088.5], [2001.4, 44.7], [1847.2, 868.8], [2288.4, 382.8]], "buffer_hull_px": [[3028.8, -843.7], [3051.2, -927.4], [3028.8, -1011.1], [2967.5, -1072.4], [2411.2, -1233.5], [2327.4, -1255.9], [2243.7, -1233.5], [2182.5, -1172.2], [1856.4, -39.0], [1833.9, 44.7], [1679.8, 868.8], [1702.2, 952.5], [1763.5, 1013.8], [1847.2, 1036.2], [1930.9, 1013.8], [1992.2, 952.5], [2433.4, 466.5]], "buffer_radius_ft": 564.2, "points": [{"model": "gfs", "rate": "10fps", "x_ft": 2164.4, "y_ft": 8309.1, "px": 2335.2, "py": -772.3}, {"model": "gfs", "rate": "20fps", "x_ft": 1082.2, "y_ft": 4154.5, "px": 2014.1, "py": 460.4}, {"model": "hrrr", "rate": "10fps", "x_ft": 4013.5, "y_ft": 8831.9, "px": 2883.8, "py": -927.4}, {"model": "hrrr", "rate": "20fps", "x_ft": 2006.7, "y_ft": 4416.0, "px": 2288.4, "py": 382.8}, {"model": "ecmwf", "rate": "10fps", "x_ft": 1039.3, "y_ft": 5555.6, "px": 2001.4, "py": 44.7}, {"model": "ecmwf", "rate": "20fps", "x_ft": 519.6, "y_ft": 2777.8, "px": 1847.2, "py": 868.8}, {"model": "icon", "rate": "10fps", "x_ft": 2382.6, "y_ft": 7863.4, "px": 2399.9, "py": -640.1}, {"model": "icon", "rate": "20fps", "x_ft": 1191.3, "y_ft": 3931.7, "px": 2046.5, "py": 526.5}, {"model": "arpege", "rate": "10fps", "x_ft": 2138.4, "y_ft": 9374.8, "px": 2327.4, "py": -1088.5}, {"model": "arpege", "rate": "20fps", "x_ft": 1069.2, "y_ft": 4687.4, "px": 2010.2, "py": 302.3}, {"model": "gem", "rate": "10fps", "x_ft": 3629.3, "y_ft": 8603.8, "px": 2769.8, "py": -859.7}, {"model": "gem", "rate": "20fps", "x_ft": 1814.6, "y_ft": 4301.9, "px": 2231.4, "py": 416.6}]}, {"altitude": 5500, "core_hull_px": [[4010.6, -3069.5], [3486.0, -3940.2], [2931.9, -2817.1], [2417.2, -1545.3], [2055.1, 73.9], [2851.8, -688.2]], "buffer_hull_px": [[4259.8, -2925.6], [4298.3, -3069.5], [4259.8, -3213.4], [3735.2, -4084.1], [3629.9, -4189.4], [3486.0, -4228.0], [3342.1, -4189.4], [3236.8, -4084.1], [2682.7, -2961.0], [2168.0, -1689.1], [2129.5, -1545.3], [1767.4, 73.9], [1805.9, 217.7], [1911.2, 323.1], [2055.1, 361.6], [2199.0, 323.1], [2995.7, -439.1], [3101.0, -544.4]], "buffer_radius_ft": 969.8, "points": [{"model": "gfs", "rate": "10fps", "x_ft": 4175.6, "y_ft": 15200.9, "px": 2931.9, "py": -2817.1}, {"model": "gfs", "rate": "20fps", "x_ft": 2087.8, "y_ft": 7600.5, "px": 2312.4, "py": -562.1}, {"model": "hrrr", "rate": "10fps", "x_ft": 7811.3, "y_ft": 16051.6, "px": 4010.6, "py": -3069.5}, {"model": "hrrr", "rate": "20fps", "x_ft": 3905.6, "y_ft": 8025.8, "px": 2851.8, "py": -688.2}, {"model": "ecmwf", "rate": "10fps", "x_ft": 2440.8, "y_ft": 10914.3, "px": 2417.2, "py": -1545.3}, {"model": "ecmwf", "rate": "20fps", "x_ft": 1220.4, "y_ft": 5457.1, "px": 2055.1, "py": 73.9}, {"model": "icon", "rate": "10fps", "x_ft": 6454.7, "y_ft": 14908.0, "px": 3608.1, "py": -2730.2}, {"model": "icon", "rate": "20fps", "x_ft": 3227.4, "y_ft": 7454.0, "px": 2650.6, "py": -518.6}, {"model": "arpege", "rate": "10fps", "x_ft": 6043.1, "y_ft": 18986.3, "px": 3486.0, "py": -3940.2}, {"model": "arpege", "rate": "20fps", "x_ft": 3021.6, "y_ft": 9493.2, "px": 2589.5, "py": -1123.6}, {"model": "gem", "rate": "10fps", "x_ft": 6927.0, "y_ft": 16680.9, "px": 3748.2, "py": -3256.2}, {"model": "gem", "rate": "20fps", "x_ft": 3463.5, "y_ft": 8340.5, "px": 2720.6, "py": -781.6}]}, {"altitude": 7800, "core_hull_px": [[5039.9, -5081.6], [4550.8, -6649.8], [3360.3, -4762.0], [2526.7, -1534.5], [2367.8, -881.1], [3293.6, -1574.4], [3366.4, -1694.3]], "buffer_hull_px": [[5393.3, -4877.5], [5447.9, -5081.6], [5393.3, -5285.6], [4904.2, -6853.8], [4754.8, -7003.2], [4550.8, -7057.8], [4346.7, -7003.2], [4197.4, -6853.8], [3006.9, -4966.0], [2952.2, -4762.0], [2118.6, -1534.5], [1959.7, -881.1], [2014.4, -677.0], [2163.8, -527.7], [2367.8, -473.0], [2571.8, -527.7], [3497.6, -1221.0], [3647.0, -1370.4], [3719.8, -1490.3]], "buffer_radius_ft": 1375.4, "points": [{"model": "gfs", "rate": "10fps", "x_ft": 5619.5, "y_ft": 21756.0, "px": 3360.3, "py": -4762.0}, {"model": "gfs", "rate": "20fps", "x_ft": 2809.8, "y_ft": 10878.0, "px": 2526.7, "py": -1534.5}, {"model": "hrrr", "rate": "10fps", "x_ft": 11280.4, "y_ft": 22833.1, "px": 5039.9, "py": -5081.6}, {"model": "hrrr", "rate": "20fps", "x_ft": 5640.2, "y_ft": 11416.6, "px": 3366.4, "py": -1694.3}, {"model": "ecmwf", "rate": "10fps", "x_ft": 4548.7, "y_ft": 17351.3, "px": 3042.6, "py": -3455.1}, {"model": "ecmwf", "rate": "20fps", "x_ft": 2274.3, "y_ft": 8675.7, "px": 2367.8, "py": -881.1}, {"model": "icon", "rate": "10fps", "x_ft": 10789.3, "y_ft": 22025.0, "px": 4894.2, "py": -4841.8}, {"model": "icon", "rate": "20fps", "x_ft": 5394.7, "y_ft": 11012.5, "px": 3293.6, "py": -1574.4}, {"model": "arpege", "rate": "10fps", "x_ft": 9631.9, "y_ft": 28118.6, "px": 4550.8, "py": -6649.8}, {"model": "arpege", "rate": "20fps", "x_ft": 4815.9, "y_ft": 14059.3, "px": 3121.9, "py": -2478.4}, {"model": "gem", "rate": "10fps", "x_ft": 10287.4, "y_ft": 25162.8, "px": 4745.3, "py": -5772.8}, {"model": "gem", "rate": "20fps", "x_ft": 5143.7, "y_ft": 12581.4, "px": 3219.1, "py": -2039.9}]}, {"altitude": 10000, "core_hull_px": [[3796.4, -2635.7], [5899.7, -6964.3], [5894.6, -8208.8], [5321.5, -8998.5], [3677.1, -6793.4], [2685.1, -2550.2], [2775.8, -1926.8]], "buffer_hull_px": [[6352.8, -6702.8], [6422.9, -6964.3], [6417.7, -8208.8], [6347.6, -8470.4], [5774.5, -9260.1], [5583.1, -9451.6], [5321.5, -9521.7], [5059.9, -9451.6], [4868.4, -9260.1], [3224.0, -7055.0], [3154.0, -6793.4], [2161.9, -2550.2], [2252.6, -1926.8], [2322.7, -1665.2], [2514.2, -1473.8], [2775.8, -1403.7], [3037.3, -1473.8], [4057.9, -2182.6], [4249.4, -2374.1]], "buffer_radius_ft": 1763.3, "points": [{"model": "gfs", "rate": "10fps", "x_ft": 6687.3, "y_ft": 28602.8, "px": 3677.1, "py": -6793.4}, {"model": "gfs", "rate": "20fps", "x_ft": 3343.7, "y_ft": 14301.4, "px": 2685.1, "py": -2550.2}, {"model": "hrrr", "rate": "10fps", "x_ft": 13853.4, "y_ft": 29696.9, "px": 5803.3, "py": -7118.0}, {"model": "hrrr", "rate": "20fps", "x_ft": 6926.7, "y_ft": 14848.5, "px": 3748.1, "py": -2712.5}, {"model": "ecmwf", "rate": "10fps", "x_ft": 7298.8, "y_ft": 24400.7, "px": 3858.5, "py": -5546.7}, {"model": "ecmwf", "rate": "20fps", "x_ft": 3649.4, "y_ft": 12200.3, "px": 2775.8, "py": -1926.8}, {"model": "icon", "rate": "10fps", "x_ft": 14178.4, "y_ft": 29178.9, "px": 5899.7, "py": -6964.3}, {"model": "icon", "rate": "20fps", "x_ft": 7089.2, "y_ft": 14589.4, "px": 3796.4, "py": -2635.7}, {"model": "arpege", "rate": "10fps", "x_ft": 12229.5, "y_ft": 36034.8, "px": 5321.5, "py": -8998.5}, {"model": "arpege", "rate": "20fps", "x_ft": 6114.8, "y_ft": 18017.4, "px": 3507.2, "py": -3652.7}, {"model": "gem", "rate": "10fps", "x_ft": 14161.1, "y_ft": 33373.4, "px": 5894.6, "py": -8208.8}, {"model": "gem", "rate": "20fps", "x_ft": 7080.5, "y_ft": 16686.7, "px": 3793.8, "py": -3257.9}]}], "11_dual": [{"altitude": 1000, "core_hull_px": [[1773.4, 1455.2], [1850.5, 1226.8], [1752.1, 1253.3], [1745.1, 1268.3], [1727.5, 1341.3], [1710.8, 1513.1], [1733.8, 1493.3]], "buffer_hull_px": [[1658.5, 1513.1], [1665.5, 1539.2], [1684.7, 1558.4], [1710.8, 1565.4], [1737.0, 1558.4], [1760.0, 1538.6], [1799.5, 1500.5], [1818.7, 1481.3], [1895.8, 1253.0], [1902.8, 1226.8], [1895.8, 1200.6], [1876.6, 1181.5], [1850.5, 1174.5], [1824.3, 1181.5], [1726.0, 1208.0], [1706.8, 1227.2], [1699.8, 1242.1], [1692.8, 1268.3], [1675.2, 1341.3]], "buffer_radius_ft": 176.3, "points": [{"model": "gfs", "rate": "slow", "x_ft": 175.5, "y_ft": 1431.4, "px": 1745.1, "py": 1268.3}, {"model": "gfs", "rate": "fast", "x_ft": 89.8, "y_ft": 730.1, "px": 1719.6, "py": 1476.4}, {"model": "hrrr", "rate": "slow", "x_ft": 516.5, "y_ft": 1560.1, "px": 1846.2, "py": 1230.1}, {"model": "hrrr", "rate": "fast", "x_ft": 263.8, "y_ft": 795.5, "px": 1771.3, "py": 1457.0}, {"model": "ecmwf", "rate": "slow", "x_ft": 269.8, "y_ft": 1320.4, "px": 1773.1, "py": 1301.2}, {"model": "ecmwf", "rate": "fast", "x_ft": 137.7, "y_ft": 673.0, "px": 1733.8, "py": 1493.3}, {"model": "icon", "rate": "slow", "x_ft": 199.3, "y_ft": 1481.9, "px": 1752.1, "py": 1253.3}, {"model": "icon", "rate": "fast", "x_ft": 102.2, "y_ft": 756.1, "px": 1723.3, "py": 1468.7}, {"model": "arpege", "rate": "slow", "x_ft": 116.2, "y_ft": 1185.3, "px": 1727.5, "py": 1341.3}, {"model": "arpege", "rate": "fast", "x_ft": 60.1, "y_ft": 606.5, "px": 1710.8, "py": 1513.1}, {"model": "gem", "rate": "slow", "x_ft": 530.7, "y_ft": 1571.3, "px": 1850.5, "py": 1226.8}, {"model": "gem", "rate": "fast", "x_ft": 270.9, "y_ft": 801.6, "px": 1773.4, "py": 1455.2}]}, {"altitude": 3200, "core_hull_px": [[1749.0, 1323.1], [1765.2, 1365.7], [1840.5, 1296.9], [1932.7, 1030.1], [1933.5, 1011.9], [1804.8, 1048.5], [1781.7, 1076.7]], "buffer_hull_px": [[1581.6, 1323.1], [1604.0, 1406.8], [1620.2, 1449.4], [1681.5, 1510.7], [1765.2, 1533.1], [1848.9, 1510.7], [1924.2, 1441.9], [1985.5, 1380.6], [2077.7, 1113.8], [2100.1, 1030.1], [2100.9, 1011.9], [2078.5, 928.2], [2017.2, 867.0], [1933.5, 844.5], [1849.8, 867.0], [1721.1, 903.5], [1659.8, 964.8], [1636.8, 993.0], [1614.3, 1076.7]], "buffer_radius_ft": 564.2, "points": [{"model": "gfs", "rate": "slow", "x_ft": 299.1, "y_ft": 2077.3, "px": 1781.7, "py": 1076.7}, {"model": "gfs", "rate": "fast", "x_ft": 188.7, "y_ft": 1246.8, "px": 1749.0, "py": 1323.1}, {"model": "hrrr", "rate": "slow", "x_ft": 808.0, "y_ft": 2234.3, "px": 1932.7, "py": 1030.1}, {"model": "hrrr", "rate": "fast", "x_ft": 497.0, "y_ft": 1334.9, "px": 1840.5, "py": 1296.9}, {"model": "ecmwf", "rate": "slow", "x_ft": 401.8, "y_ft": 1858.1, "px": 1812.2, "py": 1141.7}, {"model": "ecmwf", "rate": "fast", "x_ft": 243.2, "y_ft": 1103.1, "px": 1765.2, "py": 1365.7}, {"model": "icon", "rate": "slow", "x_ft": 376.8, "y_ft": 2172.3, "px": 1804.8, "py": 1048.5}, {"model": "icon", "rate": "fast", "x_ft": 244.2, "y_ft": 1308.4, "px": 1765.5, "py": 1304.8}, {"model": "arpege", "rate": "slow", "x_ft": 323.4, "y_ft": 1939.6, "px": 1789.0, "py": 1117.5}, {"model": "arpege", "rate": "fast", "x_ft": 225.9, "y_ft": 1209.9, "px": 1760.0, "py": 1334.0}, {"model": "gem", "rate": "slow", "x_ft": 810.5, "y_ft": 2295.4, "px": 1933.5, "py": 1011.9}, {"model": "gem", "rate": "fast", "x_ft": 494.8, "y_ft": 1380.9, "px": 1839.8, "py": 1283.3}]}, {"altitude": 5500, "core_hull_px": [[1792.8, 1134.9], [1814.6, 1201.0], [1932.5, 1104.6], [2047.7, 789.7], [2038.4, 736.7], [1836.6, 841.5]], "buffer_hull_px": [[1505.1, 1134.9], [1543.7, 1278.8], [1565.4, 1344.8], [1670.7, 1450.1], [1814.6, 1488.7], [1958.5, 1450.1], [2076.3, 1353.8], [2181.7, 1248.5], [2296.9, 933.5], [2335.5, 789.7], [2326.2, 736.7], [2287.6, 592.8], [2182.3, 487.5], [2038.4, 449.0], [1894.6, 487.5], [1692.7, 592.3], [1587.4, 697.6], [1548.8, 841.5]], "buffer_radius_ft": 969.8, "points": [{"model": "gfs", "rate": "slow", "x_ft": 483.9, "y_ft": 2869.9, "px": 1836.6, "py": 841.5}, {"model": "gfs", "rate": "fast", "x_ft": 336.5, "y_ft": 1880.9, "px": 1792.8, "py": 1134.9}, {"model": "hrrr", "rate": "slow", "x_ft": 1195.6, "y_ft": 3044.6, "px": 2047.7, "py": 789.7}, {"model": "hrrr", "rate": "fast", "x_ft": 807.1, "y_ft": 1983.1, "px": 1932.5, "py": 1104.6}, {"model": "ecmwf", "rate": "slow", "x_ft": 610.0, "y_ft": 2552.2, "px": 1874.0, "py": 935.8}, {"model": "ecmwf", "rate": "fast", "x_ft": 409.8, "y_ft": 1658.4, "px": 1814.6, "py": 1201.0}, {"model": "icon", "rate": "slow", "x_ft": 749.5, "y_ft": 2992.1, "px": 1915.4, "py": 805.2}, {"model": "icon", "rate": "fast", "x_ft": 542.4, "y_ft": 1964.3, "px": 1853.9, "py": 1110.2}, {"model": "arpege", "rate": "slow", "x_ft": 717.8, "y_ft": 2946.3, "px": 1906.0, "py": 818.8}, {"model": "arpege", "rate": "fast", "x_ft": 541.3, "y_ft": 2015.3, "px": 1853.6, "py": 1095.1}, {"model": "gem", "rate": "slow", "x_ft": 1164.3, "y_ft": 3223.2, "px": 2038.4, "py": 736.7}, {"model": "gem", "rate": "fast", "x_ft": 777.8, "y_ft": 2123.1, "px": 1923.8, "py": 1063.1}]}, {"altitude": 7800, "core_hull_px": [[1845.0, 929.6], [1884.4, 1005.7], [2030.8, 900.7], [2170.6, 534.7], [2159.9, 430.0], [1901.8, 584.8]], "buffer_hull_px": [[1493.7, 584.8], [1437.0, 929.6], [1491.6, 1133.6], [1531.0, 1209.7], [1680.4, 1359.1], [1884.4, 1413.8], [2088.5, 1359.1], [2234.8, 1254.1], [2384.1, 1104.7], [2524.0, 738.8], [2578.7, 534.7], [2568.0, 430.0], [2513.3, 226.0], [2364.0, 76.6], [2159.9, 21.9], [1955.9, 76.6], [1697.8, 231.4], [1548.4, 380.8]], "buffer_radius_ft": 1375.4, "points": [{"model": "gfs", "rate": "slow", "x_ft": 703.7, "y_ft": 3735.0, "px": 1901.8, "py": 584.8}, {"model": "gfs", "rate": "fast", "x_ft": 512.4, "y_ft": 2573.0, "px": 1845.0, "py": 929.6}, {"model": "hrrr", "rate": "slow", "x_ft": 1609.7, "y_ft": 3903.8, "px": 2170.6, "py": 534.7}, {"model": "hrrr", "rate": "fast", "x_ft": 1138.4, "y_ft": 2670.5, "px": 2030.8, "py": 900.7}, {"model": "ecmwf", "rate": "slow", "x_ft": 904.3, "y_ft": 3374.8, "px": 1961.3, "py": 691.7}, {"model": "ecmwf", "rate": "fast", "x_ft": 645.2, "y_ft": 2316.5, "px": 1884.4, "py": 1005.7}, {"model": "icon", "rate": "slow", "x_ft": 1244.6, "y_ft": 3844.8, "px": 2062.3, "py": 552.3}, {"model": "icon", "rate": "fast", "x_ft": 938.5, "y_ft": 2646.4, "px": 1971.4, "py": 907.8}, {"model": "arpege", "rate": "slow", "x_ft": 1175.9, "y_ft": 4002.1, "px": 2041.9, "py": 505.6}, {"model": "arpege", "rate": "fast", "x_ft": 907.8, "y_ft": 2860.0, "px": 1962.4, "py": 844.5}, {"model": "gem", "rate": "slow", "x_ft": 1573.7, "y_ft": 4256.9, "px": 2159.9, "py": 430.0}, {"model": "gem", "rate": "fast", "x_ft": 1105.4, "y_ft": 2950.0, "px": 2021.0, "py": 817.7}]}, {"altitude": 10000, "core_hull_px": [[1901.3, 719.6], [1971.9, 793.5], [2123.6, 702.0], [2286.7, 286.5], [2303.7, 125.5], [1972.2, 322.3]], "buffer_hull_px": [[1378.2, 719.6], [1448.2, 981.2], [1518.9, 1055.1], [1710.4, 1246.6], [1971.9, 1316.6], [2233.5, 1246.6], [2385.2, 1155.1], [2576.7, 963.6], [2739.8, 548.0], [2809.9, 286.5], [2826.8, 125.5], [2756.7, -136.1], [2565.2, -327.6], [2303.7, -397.7], [2042.1, -327.6], [1710.6, -130.7], [1519.1, 60.8], [1449.0, 322.3]], "buffer_radius_ft": 1763.3, "points": [{"model": "gfs", "rate": "slow", "x_ft": 940.9, "y_ft": 4619.7, "px": 1972.2, "py": 322.3}, {"model": "gfs", "rate": "fast", "x_ft": 702.1, "y_ft": 3280.7, "px": 1901.3, "py": 719.6}, {"model": "hrrr", "rate": "slow", "x_ft": 2001.1, "y_ft": 4740.6, "px": 2286.7, "py": 286.5}, {"model": "hrrr", "rate": "fast", "x_ft": 1451.5, "y_ft": 3340.0, "px": 2123.6, "py": 702.0}, {"model": "ecmwf", "rate": "slow", "x_ft": 1272.9, "y_ft": 4268.8, "px": 2070.7, "py": 426.4}, {"model": "ecmwf", "rate": "fast", "x_ft": 940.2, "y_ft": 3031.7, "px": 1971.9, "py": 793.5}, {"model": "icon", "rate": "slow", "x_ft": 1715.5, "y_ft": 4715.6, "px": 2202.0, "py": 293.9}, {"model": "icon", "rate": "fast", "x_ft": 1315.1, "y_ft": 3343.0, "px": 2083.2, "py": 701.1}, {"model": "arpege", "rate": "slow", "x_ft": 1572.9, "y_ft": 4958.5, "px": 2159.7, "py": 221.8}, {"model": "arpege", "rate": "fast", "x_ft": 1225.5, "y_ft": 3625.0, "px": 2056.6, "py": 617.5}, {"model": "gem", "rate": "slow", "x_ft": 2058.1, "y_ft": 5283.3, "px": 2303.7, "py": 125.5}, {"model": "gem", "rate": "fast", "x_ft": 1492.9, "y_ft": 3771.2, "px": 2135.9, "py": 574.1}]}], "11_single": [{"altitude": 1000, "core_hull_px": [[1791.1, 1404.8], [1889.3, 1116.5], [1769.6, 1148.6], [1759.2, 1168.6], [1741.3, 1245.6], [1717.1, 1469.3], [1742.6, 1452.9], [1788.9, 1407.9]], "buffer_hull_px": [[1664.8, 1469.3], [1671.8, 1495.5], [1691.0, 1514.6], [1717.1, 1521.6], [1743.3, 1514.6], [1768.7, 1498.2], [1815.1, 1453.2], [1834.2, 1434.1], [1836.4, 1430.9], [1934.6, 1142.7], [1941.6, 1116.5], [1934.6, 1090.4], [1915.4, 1071.2], [1889.3, 1064.2], [1769.6, 1096.3], [1743.4, 1103.3], [1724.3, 1122.4], [1713.9, 1142.4], [1706.9, 1168.6], [1689.0, 1245.6]], "buffer_radius_ft": 176.3, "points": [{"model": "gfs", "rate": "10fps", "x_ft": 223.2, "y_ft": 1767.5, "px": 1759.2, "py": 1168.6}, {"model": "gfs", "rate": "20fps", "x_ft": 111.6, "y_ft": 883.7, "px": 1726.1, "py": 1430.8}, {"model": "hrrr", "rate": "10fps", "x_ft": 646.4, "y_ft": 1921.6, "px": 1884.8, "py": 1122.9}, {"model": "hrrr", "rate": "20fps", "x_ft": 323.2, "y_ft": 960.8, "px": 1788.9, "py": 1407.9}, {"model": "ecmwf", "rate": "10fps", "x_ft": 334.1, "y_ft": 1618.6, "px": 1792.1, "py": 1212.8}, {"model": "ecmwf", "rate": "20fps", "x_ft": 167.1, "y_ft": 809.3, "px": 1742.6, "py": 1452.9}, {"model": "icon", "rate": "10fps", "x_ft": 258.1, "y_ft": 1834.9, "px": 1769.6, "py": 1148.6}, {"model": "icon", "rate": "20fps", "x_ft": 129.1, "y_ft": 917.5, "px": 1731.3, "py": 1420.8}, {"model": "arpege", "rate": "10fps", "x_ft": 162.8, "y_ft": 1507.9, "px": 1741.3, "py": 1245.6}, {"model": "arpege", "rate": "20fps", "x_ft": 81.4, "y_ft": 754.0, "px": 1717.1, "py": 1469.3}, {"model": "gem", "rate": "10fps", "x_ft": 661.5, "y_ft": 1942.9, "px": 1889.3, "py": 1116.5}, {"model": "gem", "rate": "20fps", "x_ft": 330.7, "y_ft": 971.4, "px": 1791.1, "py": 1404.8}]}, {"altitude": 3200, "core_hull_px": [[1872.8, 664.3], [1899.2, 814.8], [2134.9, 607.8], [2576.8, -477.4], [2553.5, -602.4], [2233.0, -544.8], [2052.6, -364.5]], "buffer_hull_px": [[1885.1, -364.5], [1705.4, 664.3], [1731.7, 814.8], [1754.2, 898.5], [1815.4, 959.7], [1899.2, 982.2], [1982.9, 959.7], [2218.6, 752.8], [2279.9, 691.5], [2721.8, -393.7], [2744.2, -477.4], [2721.0, -602.4], [2698.5, -686.1], [2637.3, -747.3], [2553.5, -769.8], [2233.0, -712.2], [2149.3, -689.8], [1968.9, -509.4], [1907.6, -448.2]], "buffer_radius_ft": 564.2, "points": [{"model": "gfs", "rate": "10fps", "x_ft": 1211.9, "y_ft": 6934.5, "px": 2052.6, "py": -364.5}, {"model": "gfs", "rate": "20fps", "x_ft": 605.9, "y_ft": 3467.3, "px": 1872.8, "py": 664.3}, {"model": "hrrr", "rate": "10fps", "x_ft": 2978.7, "y_ft": 7315.0, "px": 2576.8, "py": -477.4}, {"model": "hrrr", "rate": "20fps", "x_ft": 1489.4, "y_ft": 3657.5, "px": 2134.9, "py": 607.8}, {"model": "ecmwf", "rate": "10fps", "x_ft": 1389.6, "y_ft": 5920.1, "px": 2105.3, "py": -63.5}, {"model": "ecmwf", "rate": "20fps", "x_ft": 694.8, "y_ft": 2960.1, "px": 1899.2, "py": 814.8}, {"model": "icon", "rate": "10fps", "x_ft": 1678.5, "y_ft": 7358.1, "px": 2191.0, "py": -490.1}, {"model": "icon", "rate": "20fps", "x_ft": 839.2, "y_ft": 3679.0, "px": 1942.0, "py": 601.4}, {"model": "arpege", "rate": "10fps", "x_ft": 1820.1, "y_ft": 7542.4, "px": 2233.0, "py": -544.8}, {"model": "arpege", "rate": "20fps", "x_ft": 910.1, "y_ft": 3771.2, "px": 1963.0, "py": 574.1}, {"model": "gem", "rate": "10fps", "x_ft": 2900.4, "y_ft": 7736.3, "px": 2553.5, "py": -602.4}, {"model": "gem", "rate": "20fps", "x_ft": 1450.2, "y_ft": 3868.2, "px": 2123.3, "py": 545.3}]}, {"altitude": 5500, "core_hull_px": [[2594.9, -353.8], [3496.7, -2400.7], [3393.2, -2804.4], [3169.1, -2934.4], [2491.2, -2245.8], [2092.1, -276.4], [2146.3, -8.9]], "buffer_hull_px": [[3745.9, -2256.8], [3784.4, -2400.7], [3680.9, -2804.4], [3642.3, -2948.3], [3537.0, -3053.6], [3313.0, -3183.6], [3169.1, -3222.1], [3025.2, -3183.6], [2919.9, -3078.2], [2242.0, -2389.6], [2203.5, -2245.8], [1804.4, -276.4], [1858.6, -8.9], [1897.1, 134.9], [2002.4, 240.2], [2146.3, 278.8], [2290.2, 240.2], [2738.7, -104.6], [2844.0, -210.0]], "buffer_radius_ft": 969.8, "points": [{"model": "gfs", "rate": "10fps", "x_ft": 2690.3, "y_ft": 13275.3, "px": 2491.2, "py": -2245.8}, {"model": "gfs", "rate": "20fps", "x_ft": 1345.1, "y_ft": 6637.7, "px": 2092.1, "py": -276.4}, {"model": "hrrr", "rate": "10fps", "x_ft": 6079.3, "y_ft": 13797.4, "px": 3496.7, "py": -2400.7}, {"model": "hrrr", "rate": "20fps", "x_ft": 3039.6, "y_ft": 6898.7, "px": 2594.9, "py": -353.8}, {"model": "ecmwf", "rate": "10fps", "x_ft": 3055.7, "y_ft": 11472.6, "px": 2599.6, "py": -1710.9}, {"model": "ecmwf", "rate": "20fps", "x_ft": 1527.8, "y_ft": 5736.3, "px": 2146.3, "py": -8.9}, {"model": "icon", "rate": "10fps", "x_ft": 4660.3, "y_ft": 13917.0, "px": 3075.7, "py": -2436.1}, {"model": "icon", "rate": "20fps", "x_ft": 2330.2, "y_ft": 6958.5, "px": 2384.4, "py": -371.6}, {"model": "arpege", "rate": "10fps", "x_ft": 4975.0, "y_ft": 15596.2, "px": 3169.1, "py": -2934.4}, {"model": "arpege", "rate": "20fps", "x_ft": 2487.5, "y_ft": 7798.1, "px": 2431.0, "py": -620.7}, {"model": "gem", "rate": "10fps", "x_ft": 5730.2, "y_ft": 15158.1, "px": 3393.2, "py": -2804.4}, {"model": "gem", "rate": "20fps", "x_ft": 2865.1, "y_ft": 7579.1, "px": 2543.1, "py": -555.7}]}, {"altitude": 7800, "core_hull_px": [[3013.1, -4299.3], [2353.0, -1303.2], [2495.5, -985.3], [3086.3, -1373.5], [4479.6, -4440.1], [4365.0, -5258.0], [4256.5, -5440.5]], "buffer_hull_px": [[4833.0, -4236.0], [4887.7, -4440.1], [4773.1, -5258.0], [4718.4, -5462.0], [4609.9, -5644.5], [4460.5, -5793.9], [4256.5, -5848.6], [4052.5, -5793.9], [2809.0, -4652.7], [2659.7, -4503.4], [2605.0, -4299.3], [1945.0, -1303.2], [1999.6, -1099.1], [2142.1, -781.2], [2291.5, -631.9], [2495.5, -577.2], [2699.5, -631.9], [3290.3, -1020.1], [3439.7, -1169.5]], "buffer_radius_ft": 1375.4, "points": [{"model": "gfs", "rate": "10fps", "x_ft": 4449.2, "y_ft": 20196.7, "px": 3013.1, "py": -4299.3}, {"model": "gfs", "rate": "20fps", "x_ft": 2224.6, "y_ft": 10098.3, "px": 2353.0, "py": -1303.2}, {"model": "hrrr", "rate": "10fps", "x_ft": 9392.1, "y_ft": 20671.0, "px": 4479.6, "py": -4440.1}, {"model": "hrrr", "rate": "20fps", "x_ft": 4696.1, "y_ft": 10335.5, "px": 3086.3, "py": -1373.5}, {"model": "ecmwf", "rate": "10fps", "x_ft": 5409.6, "y_ft": 18053.8, "px": 3298.0, "py": -3663.5}, {"model": "ecmwf", "rate": "20fps", "x_ft": 2704.8, "y_ft": 9026.9, "px": 2495.5, "py": -985.3}, {"model": "icon", "rate": "10fps", "x_ft": 8621.2, "y_ft": 20738.1, "px": 4250.9, "py": -4460.0}, {"model": "icon", "rate": "20fps", "x_ft": 4310.6, "y_ft": 10369.1, "px": 2971.9, "py": -1383.5}, {"model": "arpege", "rate": "10fps", "x_ft": 8640.0, "y_ft": 24042.9, "px": 4256.5, "py": -5440.5}, {"model": "arpege", "rate": "20fps", "x_ft": 4320.0, "y_ft": 12021.5, "px": 2974.7, "py": -1873.8}, {"model": "gem", "rate": "10fps", "x_ft": 9005.8, "y_ft": 23427.7, "px": 4365.0, "py": -5258.0}, {"model": "gem", "rate": "20fps", "x_ft": 4502.9, "y_ft": 11713.9, "px": 3029.0, "py": -1782.5}]}, {"altitude": 10000, "core_hull_px": [[2634.5, -2353.1], [2933.0, -2046.3], [3550.8, -2366.7], [5408.6, -6426.3], [5514.8, -7694.2], [5198.9, -7710.5], [3576.0, -6399.1]], "buffer_hull_px": [[3052.8, -6399.1], [2111.3, -2353.1], [2181.4, -2091.5], [2480.0, -1784.7], [2671.5, -1593.2], [2933.0, -1523.1], [3194.6, -1593.2], [3812.4, -1913.6], [4003.9, -2105.1], [5861.7, -6164.7], [5931.7, -6426.3], [6038.0, -7694.2], [5967.9, -7955.8], [5776.4, -8147.3], [5514.8, -8217.4], [5198.9, -8233.6], [4937.3, -8163.5], [3314.4, -6852.2], [3122.9, -6660.7]], "buffer_radius_ft": 1763.3, "points": [{"model": "gfs", "rate": "10fps", "x_ft": 6346.5, "y_ft": 27273.8, "px": 3576.0, "py": -6399.1}, {"model": "gfs", "rate": "20fps", "x_ft": 3173.3, "y_ft": 13636.9, "px": 2634.5, "py": -2353.1}, {"model": "hrrr", "rate": "10fps", "x_ft": 12523.1, "y_ft": 27365.6, "px": 5408.6, "py": -6426.3}, {"model": "hrrr", "rate": "20fps", "x_ft": 6261.5, "y_ft": 13682.8, "px": 3550.8, "py": -2366.7}, {"model": "ecmwf", "rate": "10fps", "x_ft": 8358.9, "y_ft": 25206.1, "px": 4173.1, "py": -5785.6}, {"model": "ecmwf", "rate": "20fps", "x_ft": 4179.5, "y_ft": 12603.0, "px": 2933.0, "py": -2046.3}, {"model": "icon", "rate": "10fps", "x_ft": 12387.8, "y_ft": 27704.5, "px": 5368.4, "py": -6526.9}, {"model": "icon", "rate": "20fps", "x_ft": 6193.9, "y_ft": 13852.2, "px": 3530.7, "py": -2416.9}, {"model": "arpege", "rate": "10fps", "x_ft": 11816.2, "y_ft": 31693.6, "px": 5198.9, "py": -7710.5}, {"model": "arpege", "rate": "20fps", "x_ft": 5908.1, "y_ft": 15846.8, "px": 3445.9, "py": -3008.7}, {"model": "gem", "rate": "10fps", "x_ft": 12881.2, "y_ft": 31638.9, "px": 5514.8, "py": -7694.2}, {"model": "gem", "rate": "20fps", "x_ft": 6440.6, "y_ft": 15819.4, "px": 3603.9, "py": -3000.6}]}], "13_dual": [{"altitude": 1000, "core_hull_px": [[1812.6, 1246.5], [1656.3, 1265.6], [1674.6, 1475.1], [1697.3, 1534.3], [1739.5, 1501.7], [1754.0, 1465.5]], "buffer_hull_px": [[1838.8, 1201.2], [1812.6, 1194.2], [1656.3, 1213.3], [1630.2, 1220.3], [1611.0, 1239.4], [1604.0, 1265.6], [1622.2, 1475.1], [1629.2, 1501.3], [1652.0, 1560.5], [1671.1, 1579.7], [1697.3, 1586.7], [1723.5, 1579.7], [1765.6, 1547.0], [1784.8, 1527.9], [1799.3, 1491.6], [1865.0, 1246.5], [1857.9, 1220.4]], "buffer_radius_ft": 176.3, "points": [{"model": "gfs", "rate": "slow", "x_ft": -123.7, "y_ft": 1440.6, "px": 1656.3, "py": 1265.6}, {"model": "gfs", "rate": "fast", "x_ft": -62.2, "y_ft": 734.3, "px": 1674.6, "py": 1475.1}, {"model": "hrrr", "rate": "slow", "x_ft": 231.3, "y_ft": 1366.2, "px": 1761.6, "py": 1287.7}, {"model": "hrrr", "rate": "fast", "x_ft": 118.5, "y_ft": 696.2, "px": 1728.2, "py": 1486.4}, {"model": "ecmwf", "rate": "slow", "x_ft": 307.0, "y_ft": 1264.7, "px": 1784.1, "py": 1317.8}, {"model": "ecmwf", "rate": "fast", "x_ft": 156.6, "y_ft": 644.7, "px": 1739.5, "py": 1501.7}, {"model": "icon", "rate": "slow", "x_ft": 317.5, "y_ft": 1472.6, "px": 1787.2, "py": 1256.1}, {"model": "icon", "rate": "fast", "x_ft": 162.4, "y_ft": 751.5, "px": 1741.2, "py": 1470.0}, {"model": "arpege", "rate": "slow", "x_ft": 27.8, "y_ft": 1046.7, "px": 1701.2, "py": 1382.4}, {"model": "arpege", "rate": "fast", "x_ft": 14.5, "y_ft": 534.7, "px": 1697.3, "py": 1534.3}, {"model": "gem", "rate": "slow", "x_ft": 403.2, "y_ft": 1504.8, "px": 1812.6, "py": 1246.5}, {"model": "gem", "rate": "fast", "x_ft": 205.5, "y_ft": 766.8, "px": 1754.0, "py": 1465.5}]}, {"altitude": 3200, "core_hull_px": [[1715.8, 1396.7], [1775.4, 1378.4], [1792.2, 1324.0], [1860.5, 1069.7], [1851.3, 1044.5], [1678.4, 1092.3], [1692.2, 1336.5]], "buffer_hull_px": [[1511.0, 1092.3], [1524.8, 1336.5], [1547.2, 1420.2], [1570.8, 1480.4], [1632.1, 1541.7], [1715.8, 1564.1], [1799.5, 1541.7], [1859.1, 1523.4], [1920.4, 1462.1], [1937.2, 1407.8], [2005.5, 1153.4], [2027.9, 1069.7], [2005.5, 986.0], [1996.3, 960.8], [1935.0, 899.5], [1851.3, 877.1], [1767.6, 899.5], [1594.7, 947.3], [1533.4, 1008.6]], "buffer_radius_ft": 564.2, "points": [{"model": "gfs", "rate": "slow", "x_ft": -49.3, "y_ft": 2024.5, "px": 1678.4, "py": 1092.3}, {"model": "gfs", "rate": "fast", "x_ft": -2.7, "y_ft": 1201.4, "px": 1692.2, "py": 1336.5}, {"model": "hrrr", "rate": "slow", "x_ft": 425.2, "y_ft": 1904.8, "px": 1819.1, "py": 1127.8}, {"model": "hrrr", "rate": "fast", "x_ft": 273.7, "y_ft": 1127.1, "px": 1774.2, "py": 1358.6}, {"model": "ecmwf", "rate": "slow", "x_ft": 458.4, "y_ft": 1784.3, "px": 1829.0, "py": 1163.6}, {"model": "ecmwf", "rate": "fast", "x_ft": 277.8, "y_ft": 1060.3, "px": 1775.4, "py": 1378.4}, {"model": "icon", "rate": "slow", "x_ft": 533.6, "y_ft": 2185.6, "px": 1851.3, "py": 1044.5}, {"model": "icon", "rate": "fast", "x_ft": 335.3, "y_ft": 1322.0, "px": 1792.5, "py": 1300.8}, {"model": "arpege", "rate": "slow", "x_ft": 105.6, "y_ft": 1626.5, "px": 1724.3, "py": 1210.4}, {"model": "arpege", "rate": "fast", "x_ft": 76.7, "y_ft": 998.6, "px": 1715.8, "py": 1396.7}, {"model": "gem", "rate": "slow", "x_ft": 564.5, "y_ft": 2100.7, "px": 1860.5, "py": 1069.7}, {"model": "gem", "rate": "fast", "x_ft": 334.5, "y_ft": 1243.5, "px": 1792.2, "py": 1324.0}]}, {"altitude": 5500, "core_hull_px": [[1957.0, 796.0], [1740.5, 869.3], [1741.9, 1158.1], [1774.8, 1189.7], [1832.6, 1218.4], [1859.1, 1179.0]], "buffer_hull_px": [[2244.8, 796.0], [2206.2, 652.1], [2100.9, 546.8], [1957.0, 508.2], [1813.1, 546.8], [1596.6, 620.1], [1491.3, 725.4], [1452.7, 869.3], [1454.1, 1158.1], [1492.7, 1302.0], [1598.0, 1407.3], [1630.9, 1438.9], [1688.7, 1467.6], [1832.6, 1506.2], [1976.4, 1467.6], [2081.7, 1362.3], [2108.3, 1322.9], [2146.8, 1179.0]], "buffer_radius_ft": 969.8, "points": [{"model": "gfs", "rate": "slow", "x_ft": 160.0, "y_ft": 2776.3, "px": 1740.5, "py": 869.3}, {"model": "gfs", "rate": "fast", "x_ft": 164.7, "y_ft": 1802.8, "px": 1741.9, "py": 1158.1}, {"model": "hrrr", "rate": "slow", "x_ft": 782.9, "y_ft": 2661.4, "px": 1925.3, "py": 903.4}, {"model": "hrrr", "rate": "fast", "x_ft": 559.8, "y_ft": 1732.4, "px": 1859.1, "py": 1179.0}, {"model": "ecmwf", "rate": "slow", "x_ft": 699.2, "y_ft": 2458.3, "px": 1900.4, "py": 963.6}, {"model": "ecmwf", "rate": "fast", "x_ft": 470.4, "y_ft": 1599.5, "px": 1832.6, "py": 1218.4}, {"model": "icon", "rate": "slow", "x_ft": 889.8, "y_ft": 3023.4, "px": 1957.0, "py": 796.0}, {"model": "icon", "rate": "fast", "x_ft": 620.3, "y_ft": 1992.2, "px": 1877.0, "py": 1101.9}, {"model": "arpege", "rate": "slow", "x_ft": 354.1, "y_ft": 2498.7, "px": 1798.1, "py": 951.6}, {"model": "arpege", "rate": "fast", "x_ft": 275.6, "y_ft": 1696.3, "px": 1774.8, "py": 1189.7}, {"model": "gem", "rate": "slow", "x_ft": 827.7, "y_ft": 2917.3, "px": 1938.6, "py": 827.5}, {"model": "gem", "rate": "fast", "x_ft": 545.1, "y_ft": 1896.7, "px": 1854.7, "py": 1130.2}]}, {"altitude": 7800, "core_hull_px": [[1809.8, 954.2], [1913.6, 1028.8], [1966.3, 966.1], [2087.5, 539.5], [2049.5, 535.1], [1825.4, 614.4]], "buffer_hull_px": [[1621.4, 261.0], [1472.0, 410.4], [1417.4, 614.4], [1401.8, 954.2], [1456.4, 1158.2], [1605.8, 1307.6], [1709.5, 1382.2], [1913.6, 1436.8], [2117.6, 1382.2], [2267.0, 1232.8], [2319.7, 1170.1], [2440.9, 743.6], [2495.5, 539.5], [2440.9, 335.5], [2291.5, 186.2], [2087.5, 131.5], [2049.5, 127.1], [1845.5, 181.7]], "buffer_radius_ft": 1375.4, "points": [{"model": "gfs", "rate": "slow", "x_ft": 446.3, "y_ft": 3635.3, "px": 1825.4, "py": 614.4}, {"model": "gfs", "rate": "fast", "x_ft": 393.8, "y_ft": 2490.0, "px": 1809.8, "py": 954.2}, {"model": "hrrr", "rate": "slow", "x_ft": 1234.4, "y_ft": 3558.4, "px": 2059.2, "py": 637.2}, {"model": "hrrr", "rate": "fast", "x_ft": 921.0, "y_ft": 2450.0, "px": 1966.3, "py": 966.1}, {"model": "ecmwf", "rate": "slow", "x_ft": 1040.5, "y_ft": 3257.3, "px": 2001.7, "py": 726.6}, {"model": "ecmwf", "rate": "fast", "x_ft": 743.4, "y_ft": 2238.7, "px": 1913.6, "py": 1028.8}, {"model": "icon", "rate": "slow", "x_ft": 1329.5, "y_ft": 3887.6, "px": 2087.5, "py": 539.5}, {"model": "icon", "rate": "fast", "x_ft": 972.0, "y_ft": 2683.6, "px": 1981.4, "py": 896.8}, {"model": "arpege", "rate": "slow", "x_ft": 755.1, "y_ft": 3491.6, "px": 1917.0, "py": 657.1}, {"model": "arpege", "rate": "fast", "x_ft": 596.4, "y_ft": 2490.6, "px": 1869.9, "py": 954.0}, {"model": "gem", "rate": "slow", "x_ft": 1201.7, "y_ft": 3902.5, "px": 2049.5, "py": 535.1}, {"model": "gem", "rate": "fast", "x_ft": 844.2, "y_ft": 2684.9, "px": 1943.5, "py": 896.4}]}, {"altitude": 10000, "core_hull_px": [[1874.3, 747.7], [2015.2, 823.2], [2066.8, 760.7], [2220.0, 279.5], [2178.5, 232.6], [1906.0, 356.3]], "buffer_hull_px": [[1351.1, 747.7], [1421.2, 1009.3], [1612.7, 1200.8], [1753.7, 1276.3], [2015.2, 1346.4], [2276.8, 1276.3], [2468.3, 1084.8], [2519.8, 1022.2], [2673.0, 541.1], [2743.1, 279.5], [2673.0, 17.9], [2631.6, -29.0], [2440.1, -220.5], [2178.5, -290.6], [1917.0, -220.5], [1644.4, -96.8], [1452.9, 94.7], [1382.8, 356.3]], "buffer_radius_ft": 1763.3, "points": [{"model": "gfs", "rate": "slow", "x_ft": 717.9, "y_ft": 4505.2, "px": 1906.0, "py": 356.3}, {"model": "gfs", "rate": "fast", "x_ft": 611.1, "y_ft": 3186.0, "px": 1874.3, "py": 747.7}, {"model": "hrrr", "rate": "slow", "x_ft": 1657.8, "y_ft": 4423.9, "px": 2184.9, "py": 380.4}, {"model": "hrrr", "rate": "fast", "x_ft": 1259.8, "y_ft": 3142.4, "px": 2066.8, "py": 760.7}, {"model": "ecmwf", "rate": "slow", "x_ft": 1468.8, "y_ft": 4123.5, "px": 2128.8, "py": 469.6}, {"model": "ecmwf", "rate": "fast", "x_ft": 1086.1, "y_ft": 2931.6, "px": 2015.2, "py": 823.2}, {"model": "icon", "rate": "slow", "x_ft": 1776.1, "y_ft": 4764.1, "px": 2220.0, "py": 279.5}, {"model": "icon", "rate": "fast", "x_ft": 1329.3, "y_ft": 3384.8, "px": 2087.4, "py": 688.7}, {"model": "arpege", "rate": "slow", "x_ft": 1176.2, "y_ft": 4399.9, "px": 2042.0, "py": 387.6}, {"model": "arpege", "rate": "fast", "x_ft": 933.3, "y_ft": 3217.3, "px": 1969.9, "py": 738.4}, {"model": "gem", "rate": "slow", "x_ft": 1636.5, "y_ft": 4922.2, "px": 2178.5, "py": 232.6}, {"model": "gem", "rate": "fast", "x_ft": 1192.1, "y_ft": 3500.7, "px": 2046.7, "py": 654.4}]}], "13_single": [{"altitude": 1000, "core_hull_px": [[1839.3, 1146.9], [1653.9, 1168.7], [1673.5, 1430.9], [1699.3, 1498.4], [1749.4, 1462.9], [1766.2, 1419.9]], "buffer_hull_px": [[1601.6, 1168.7], [1621.1, 1430.9], [1628.2, 1457.0], [1654.0, 1524.5], [1673.1, 1543.7], [1699.3, 1550.7], [1725.4, 1543.7], [1775.6, 1508.2], [1794.7, 1489.0], [1811.5, 1446.1], [1891.7, 1146.9], [1884.6, 1120.7], [1865.5, 1101.6], [1839.3, 1094.5], [1653.9, 1116.4], [1627.8, 1123.4], [1608.6, 1142.6]], "buffer_radius_ft": 176.3, "points": [{"model": "gfs", "rate": "10fps", "x_ft": -131.7, "y_ft": 1767.0, "px": 1653.9, "py": 1168.7}, {"model": "gfs", "rate": "20fps", "x_ft": -65.9, "y_ft": 883.5, "px": 1673.5, "py": 1430.9}, {"model": "hrrr", "rate": "10fps", "x_ft": 299.4, "y_ft": 1672.4, "px": 1781.8, "py": 1196.8}, {"model": "hrrr", "rate": "20fps", "x_ft": 149.7, "y_ft": 836.2, "px": 1737.4, "py": 1444.9}, {"model": "ecmwf", "rate": "10fps", "x_ft": 380.3, "y_ft": 1551.2, "px": 1805.8, "py": 1232.7}, {"model": "ecmwf", "rate": "20fps", "x_ft": 190.2, "y_ft": 775.6, "px": 1749.4, "py": 1462.9}, {"model": "icon", "rate": "10fps", "x_ft": 402.5, "y_ft": 1828.6, "px": 1812.4, "py": 1150.5}, {"model": "icon", "rate": "20fps", "x_ft": 201.2, "y_ft": 914.3, "px": 1752.7, "py": 1421.7}, {"model": "arpege", "rate": "10fps", "x_ft": 42.3, "y_ft": 1312.1, "px": 1705.5, "py": 1303.7}, {"model": "arpege", "rate": "20fps", "x_ft": 21.1, "y_ft": 656.0, "px": 1699.3, "py": 1498.4}, {"model": "gem", "rate": "10fps", "x_ft": 493.2, "y_ft": 1840.7, "px": 1839.3, "py": 1146.9}, {"model": "gem", "rate": "20fps", "x_ft": 246.6, "y_ft": 920.4, "px": 1766.2, "py": 1419.9}]}, {"altitude": 3200, "core_hull_px": [[1830.4, -217.3], [1761.7, 737.9], [1791.6, 810.3], [1929.2, 846.3], [1967.5, 805.7], [2242.1, -81.7], [2325.4, -542.1]], "buffer_hull_px": [[1662.9, -217.3], [1594.3, 737.9], [1616.7, 821.6], [1646.6, 894.0], [1707.9, 955.2], [1791.6, 977.7], [1929.2, 1013.7], [2012.9, 991.3], [2074.2, 930.0], [2112.5, 889.4], [2387.0, 2.0], [2409.5, -81.7], [2492.8, -542.1], [2470.3, -625.8], [2409.1, -687.1], [2325.4, -709.5], [2241.7, -687.1], [1746.7, -362.2], [1685.4, -301.0]], "buffer_radius_ft": 564.2, "points": [{"model": "gfs", "rate": "10fps", "x_ft": 463.0, "y_ft": 6438.4, "px": 1830.4, "py": -217.3}, {"model": "gfs", "rate": "20fps", "x_ft": 231.5, "y_ft": 3219.2, "px": 1761.7, "py": 737.9}, {"model": "hrrr", "rate": "10fps", "x_ft": 1850.6, "y_ft": 5981.4, "px": 2242.1, "py": -81.7}, {"model": "hrrr", "rate": "20fps", "x_ft": 925.3, "y_ft": 2990.7, "px": 1967.5, "py": 805.7}, {"model": "ecmwf", "rate": "10fps", "x_ft": 1592.1, "y_ft": 5707.5, "px": 2165.4, "py": -0.4}, {"model": "ecmwf", "rate": "20fps", "x_ft": 796.1, "y_ft": 2853.7, "px": 1929.2, "py": 846.3}, {"model": "icon", "rate": "10fps", "x_ft": 2131.3, "y_ft": 7533.2, "px": 2325.4, "py": -542.1}, {"model": "icon", "rate": "20fps", "x_ft": 1065.7, "y_ft": 3766.6, "px": 2009.2, "py": 575.5}, {"model": "arpege", "rate": "10fps", "x_ft": 664.4, "y_ft": 5950.4, "px": 1890.1, "py": -72.5}, {"model": "arpege", "rate": "20fps", "x_ft": 332.2, "y_ft": 2975.2, "px": 1791.6, "py": 810.3}, {"model": "gem", "rate": "10fps", "x_ft": 1783.5, "y_ft": 6607.8, "px": 2222.2, "py": -267.5}, {"model": "gem", "rate": "20fps", "x_ft": 891.7, "y_ft": 3303.9, "px": 1957.6, "py": 712.7}]}, {"altitude": 5500, "core_hull_px": [[2010.1, -154.3], [2214.9, 46.4], [2392.1, -92.3], [3091.1, -1877.5], [3171.0, -2530.5], [2480.0, -2142.6], [2327.1, -2001.6]], "buffer_hull_px": [[2039.4, -2001.6], [1722.3, -154.3], [1760.9, -10.4], [1866.2, 94.9], [2071.0, 295.6], [2214.9, 334.2], [2358.7, 295.6], [2535.9, 156.9], [2641.2, 51.6], [3340.3, -1733.7], [3378.9, -1877.5], [3458.7, -2530.5], [3420.2, -2674.4], [3314.8, -2779.7], [3171.0, -2818.3], [3027.1, -2779.7], [2336.2, -2391.8], [2183.2, -2250.8], [2077.9, -2145.5]], "buffer_radius_ft": 969.8, "points": [{"model": "gfs", "rate": "10fps", "x_ft": 2137.2, "y_ft": 12452.5, "px": 2327.1, "py": -2001.6}, {"model": "gfs", "rate": "20fps", "x_ft": 1068.6, "y_ft": 6226.2, "px": 2010.1, "py": -154.3}, {"model": "hrrr", "rate": "10fps", "x_ft": 4712.3, "y_ft": 12034.3, "px": 3091.1, "py": -1877.5}, {"model": "hrrr", "rate": "20fps", "x_ft": 2356.1, "y_ft": 6017.1, "px": 2392.1, "py": -92.3}, {"model": "ecmwf", "rate": "10fps", "x_ft": 3517.9, "y_ft": 11099.3, "px": 2736.8, "py": -1600.1}, {"model": "ecmwf", "rate": "20fps", "x_ft": 1758.9, "y_ft": 5549.6, "px": 2214.9, "py": 46.4}, {"model": "icon", "rate": "10fps", "x_ft": 4981.4, "y_ft": 14235.1, "px": 3171.0, "py": -2530.5}, {"model": "icon", "rate": "20fps", "x_ft": 2490.7, "y_ft": 7117.5, "px": 2432.0, "py": -418.8}, {"model": "arpege", "rate": "10fps", "x_ft": 2652.7, "y_ft": 12927.6, "px": 2480.0, "py": -2142.6}, {"model": "arpege", "rate": "20fps", "x_ft": 1326.3, "y_ft": 6463.8, "px": 2086.5, "py": -224.8}, {"model": "gem", "rate": "10fps", "x_ft": 3889.3, "y_ft": 13140.1, "px": 2846.9, "py": -2205.6}, {"model": "gem", "rate": "20fps", "x_ft": 1944.6, "y_ft": 6570.0, "px": 2270.0, "py": -256.3}]}, {"altitude": 7800, "core_hull_px": [[2349.9, -1173.8], [2620.0, -901.9], [2927.9, -1156.8], [4162.8, -4006.5], [4214.5, -4581.9], [3734.6, -4544.2], [3431.9, -4499.3], [3006.8, -4040.6]], "buffer_hull_px": [[2598.7, -4040.6], [1941.8, -1173.8], [1996.5, -969.7], [2266.6, -697.9], [2415.9, -548.5], [2620.0, -493.9], [2824.0, -548.5], [3131.9, -803.4], [3281.3, -952.7], [4516.2, -3802.5], [4570.9, -4006.5], [4622.6, -4581.9], [4567.9, -4785.9], [4418.5, -4935.3], [4214.5, -4989.9], [3734.6, -4952.2], [3431.9, -4907.4], [3227.9, -4852.7], [3078.5, -4703.4], [2653.4, -4244.6]], "buffer_radius_ft": 1375.4, "points": [{"model": "gfs", "rate": "10fps", "x_ft": 4428.0, "y_ft": 19324.5, "px": 3006.8, "py": -4040.6}, {"model": "gfs", "rate": "20fps", "x_ft": 2214.0, "y_ft": 9662.3, "px": 2349.9, "py": -1173.8}, {"model": "hrrr", "rate": "10fps", "x_ft": 8324.3, "y_ft": 19209.7, "px": 4162.8, "py": -4006.5}, {"model": "hrrr", "rate": "20fps", "x_ft": 4162.2, "y_ft": 9604.9, "px": 2927.9, "py": -1156.8}, {"model": "ecmwf", "rate": "10fps", "x_ft": 6248.5, "y_ft": 17492.0, "px": 3546.9, "py": -3496.9}, {"model": "ecmwf", "rate": "20fps", "x_ft": 3124.3, "y_ft": 8746.0, "px": 2620.0, "py": -901.9}, {"model": "icon", "rate": "10fps", "x_ft": 8498.5, "y_ft": 21148.9, "px": 4214.5, "py": -4581.9}, {"model": "icon", "rate": "20fps", "x_ft": 4249.3, "y_ft": 10574.5, "px": 2953.8, "py": -1444.4}, {"model": "arpege", "rate": "10fps", "x_ft": 5861.0, "y_ft": 20870.8, "px": 3431.9, "py": -4499.3}, {"model": "arpege", "rate": "20fps", "x_ft": 2930.5, "y_ft": 10435.4, "px": 2562.5, "py": -1403.2}, {"model": "gem", "rate": "10fps", "x_ft": 6881.0, "y_ft": 21021.9, "px": 3734.6, "py": -4544.2}, {"model": "gem", "rate": "20fps", "x_ft": 3440.5, "y_ft": 10511.0, "px": 2713.8, "py": -1425.6}]}, {"altitude": 10000, "core_hull_px": [[5274.6, -6662.4], [4766.6, -6964.5], [3651.4, -6105.5], [2672.2, -2206.2], [3128.2, -1929.8], [3430.4, -2184.0], [5167.8, -6060.9]], "buffer_hull_px": [[3883.5, -1922.4], [5620.8, -5799.4], [5690.9, -6060.9], [5797.7, -6662.4], [5727.6, -6923.9], [5536.2, -7115.4], [5028.2, -7417.6], [4766.6, -7487.6], [4505.0, -7417.6], [3389.8, -6558.5], [3198.3, -6367.0], [3128.2, -6105.5], [2149.0, -2206.2], [2219.1, -1944.6], [2410.6, -1753.2], [2866.7, -1476.8], [3128.2, -1406.7], [3389.8, -1476.8], [3692.0, -1730.9]], "buffer_radius_ft": 1763.3, "points": [{"model": "gfs", "rate": "10fps", "x_ft": 6600.6, "y_ft": 26284.1, "px": 3651.4, "py": -6105.5}, {"model": "gfs", "rate": "20fps", "x_ft": 3300.3, "y_ft": 13142.0, "px": 2672.2, "py": -2206.2}, {"model": "hrrr", "rate": "10fps", "x_ft": 11711.4, "y_ft": 26134.0, "px": 5167.8, "py": -6060.9}, {"model": "hrrr", "rate": "20fps", "x_ft": 5855.7, "y_ft": 13067.0, "px": 3430.4, "py": -2184.0}, {"model": "ecmwf", "rate": "10fps", "x_ft": 9674.7, "y_ft": 24420.9, "px": 4563.5, "py": -5552.7}, {"model": "ecmwf", "rate": "20fps", "x_ft": 4837.3, "y_ft": 12210.5, "px": 3128.2, "py": -1929.8}, {"model": "icon", "rate": "10fps", "x_ft": 12071.4, "y_ft": 28161.1, "px": 5274.6, "py": -6662.4}, {"model": "icon", "rate": "20fps", "x_ft": 6035.7, "y_ft": 14080.6, "px": 3483.8, "py": -2484.7}, {"model": "arpege", "rate": "10fps", "x_ft": 9229.9, "y_ft": 28137.4, "px": 4431.5, "py": -6655.3}, {"model": "arpege", "rate": "20fps", "x_ft": 4614.9, "y_ft": 14068.7, "px": 3062.2, "py": -2481.2}, {"model": "gem", "rate": "10fps", "x_ft": 10359.3, "y_ft": 29179.4, "px": 4766.6, "py": -6964.5}, {"model": "gem", "rate": "20fps", "x_ft": 5179.7, "y_ft": 14589.7, "px": 3229.8, "py": -2635.7}]}], "15_dual": [{"altitude": 1000, "core_hull_px": [[1749.1, 1199.6], [1570.1, 1243.6], [1630.8, 1463.9], [1669.8, 1522.5], [1729.2, 1487.7], [1763.8, 1290.1]], "buffer_hull_px": [[1517.8, 1243.6], [1524.8, 1269.8], [1585.5, 1490.1], [1624.5, 1548.7], [1643.6, 1567.8], [1669.8, 1574.8], [1695.9, 1567.8], [1755.3, 1533.0], [1774.5, 1513.9], [1781.5, 1487.7], [1816.2, 1290.1], [1801.4, 1199.6], [1794.4, 1173.5], [1775.2, 1154.3], [1749.1, 1147.3], [1570.1, 1191.3], [1544.0, 1198.3], [1524.8, 1217.5]], "buffer_radius_ft": 176.3, "points": [{"model": "gfs", "rate": "slow", "x_ft": -414.1, "y_ft": 1514.6, "px": 1570.1, "py": 1243.6}, {"model": "gfs", "rate": "fast", "x_ft": -209.7, "y_ft": 772.1, "px": 1630.8, "py": 1463.9}, {"model": "hrrr", "rate": "slow", "x_ft": 238.8, "y_ft": 1358.0, "px": 1763.8, "py": 1290.1}, {"model": "hrrr", "rate": "fast", "x_ft": 121.9, "y_ft": 691.9, "px": 1729.2, "py": 1487.7}, {"model": "ecmwf", "rate": "slow", "x_ft": 144.9, "y_ft": 1346.0, "px": 1736.0, "py": 1293.7}, {"model": "ecmwf", "rate": "fast", "x_ft": 74.1, "y_ft": 685.9, "px": 1715.0, "py": 1489.5}, {"model": "icon", "rate": "slow", "x_ft": 217.9, "y_ft": 1459.4, "px": 1757.6, "py": 1260.0}, {"model": "icon", "rate": "fast", "x_ft": 111.2, "y_ft": 744.1, "px": 1726.0, "py": 1472.2}, {"model": "arpege", "rate": "slow", "x_ft": -154.3, "y_ft": 1125.0, "px": 1647.2, "py": 1359.2}, {"model": "arpege", "rate": "fast", "x_ft": -78.3, "y_ft": 574.7, "px": 1669.8, "py": 1522.5}, {"model": "gem", "rate": "slow", "x_ft": 189.0, "y_ft": 1662.9, "px": 1749.1, "py": 1199.6}, {"model": "gem", "rate": "fast", "x_ft": 96.4, "y_ft": 847.1, "px": 1721.6, "py": 1441.7}]}, {"altitude": 3200, "core_hull_px": [[1777.7, 1014.0], [1580.2, 1061.7], [1638.9, 1318.4], [1672.8, 1375.8], [1760.7, 1362.6], [1803.2, 1133.7], [1792.3, 1075.6]], "buffer_hull_px": [[1412.8, 1061.7], [1471.4, 1318.4], [1493.9, 1402.1], [1527.8, 1459.5], [1589.1, 1520.8], [1672.8, 1543.2], [1760.7, 1530.0], [1844.4, 1507.6], [1905.7, 1446.3], [1928.1, 1362.6], [1970.6, 1133.7], [1959.7, 1075.6], [1945.1, 1014.0], [1922.7, 930.3], [1861.4, 869.0], [1777.7, 846.5], [1580.2, 894.3], [1496.5, 916.7], [1435.2, 978.0]], "buffer_radius_ft": 564.2, "points": [{"model": "gfs", "rate": "slow", "x_ft": -380.1, "y_ft": 2127.6, "px": 1580.2, "py": 1061.7}, {"model": "gfs", "rate": "fast", "x_ft": -182.5, "y_ft": 1262.6, "px": 1638.9, "py": 1318.4}, {"model": "hrrr", "rate": "slow", "x_ft": 371.5, "y_ft": 1885.0, "px": 1803.2, "py": 1133.7}, {"model": "hrrr", "rate": "fast", "x_ft": 228.1, "y_ft": 1113.5, "px": 1760.7, "py": 1362.6}, {"model": "ecmwf", "rate": "slow", "x_ft": 247.4, "y_ft": 1883.7, "px": 1766.4, "py": 1134.1}, {"model": "ecmwf", "rate": "fast", "x_ft": 156.2, "y_ft": 1116.1, "px": 1739.3, "py": 1361.9}, {"model": "icon", "rate": "slow", "x_ft": 334.6, "y_ft": 2081.1, "px": 1792.3, "py": 1075.6}, {"model": "icon", "rate": "fast", "x_ft": 204.6, "y_ft": 1241.4, "px": 1753.7, "py": 1324.7}, {"model": "arpege", "rate": "slow", "x_ft": -141.5, "y_ft": 1743.0, "px": 1651.0, "py": 1175.8}, {"model": "arpege", "rate": "fast", "x_ft": -68.1, "y_ft": 1069.1, "px": 1672.8, "py": 1375.8}, {"model": "gem", "rate": "slow", "x_ft": 285.4, "y_ft": 2288.7, "px": 1777.7, "py": 1014.0}, {"model": "gem", "rate": "fast", "x_ft": 173.6, "y_ft": 1347.7, "px": 1744.5, "py": 1293.1}]}, {"altitude": 5500, "core_hull_px": [[1852.4, 769.8], [1637.6, 858.0], [1684.7, 1155.4], [1788.0, 1201.3], [1829.7, 1200.1], [1889.6, 930.5]], "buffer_hull_px": [[1349.8, 858.0], [1397.0, 1155.4], [1435.5, 1299.3], [1540.9, 1404.6], [1644.2, 1450.5], [1788.0, 1489.1], [1829.7, 1487.8], [1973.6, 1449.2], [2078.9, 1343.9], [2117.5, 1200.1], [2177.3, 930.5], [2140.2, 769.8], [2101.6, 625.9], [1996.3, 520.6], [1852.4, 482.0], [1708.6, 520.6], [1493.7, 608.8], [1388.4, 714.1]], "buffer_radius_ft": 969.8, "points": [{"model": "gfs", "rate": "slow", "x_ft": -186.9, "y_ft": 2814.3, "px": 1637.6, "py": 858.0}, {"model": "gfs", "rate": "fast", "x_ft": -27.9, "y_ft": 1811.9, "px": 1684.7, "py": 1155.4}, {"model": "hrrr", "rate": "slow", "x_ft": 662.5, "y_ft": 2569.8, "px": 1889.6, "py": 930.5}, {"model": "hrrr", "rate": "fast", "x_ft": 460.9, "y_ft": 1661.4, "px": 1829.7, "py": 1200.1}, {"model": "ecmwf", "rate": "slow", "x_ft": 452.6, "y_ft": 2560.0, "px": 1827.3, "py": 933.5}, {"model": "ecmwf", "rate": "fast", "x_ft": 320.3, "y_ft": 1657.2, "px": 1788.0, "py": 1201.3}, {"model": "icon", "rate": "slow", "x_ft": 539.7, "y_ft": 2794.9, "px": 1853.1, "py": 863.8}, {"model": "icon", "rate": "fast", "x_ft": 368.7, "y_ft": 1812.4, "px": 1802.4, "py": 1155.3}, {"model": "arpege", "rate": "slow", "x_ft": 117.5, "y_ft": 2634.5, "px": 1727.9, "py": 911.3}, {"model": "arpege", "rate": "fast", "x_ft": 139.1, "y_ft": 1782.3, "px": 1734.3, "py": 1164.2}, {"model": "gem", "rate": "slow", "x_ft": 537.4, "y_ft": 3111.6, "px": 1852.4, "py": 769.8}, {"model": "gem", "rate": "fast", "x_ft": 375.1, "y_ft": 2006.1, "px": 1804.3, "py": 1097.8}]}, {"altitude": 7800, "core_hull_px": [[1977.3, 486.0], [1718.0, 647.8], [1749.1, 987.3], [1866.6, 1017.0], [1931.7, 1011.6], [2017.0, 694.9]], "buffer_hull_px": [[1310.0, 647.8], [1341.0, 987.3], [1395.7, 1191.3], [1545.1, 1340.7], [1749.1, 1395.4], [1866.6, 1425.0], [1931.7, 1419.6], [2135.7, 1365.0], [2285.1, 1215.6], [2370.4, 899.0], [2425.1, 694.9], [2385.4, 486.0], [2330.7, 282.0], [2181.3, 132.6], [1977.3, 77.9], [1773.3, 132.6], [1514.0, 294.4], [1364.6, 443.8]], "buffer_radius_ft": 1375.4, "points": [{"model": "gfs", "rate": "slow", "x_ft": 84.3, "y_ft": 3522.6, "px": 1718.0, "py": 647.8}, {"model": "gfs", "rate": "fast", "x_ft": 189.1, "y_ft": 2378.5, "px": 1749.1, "py": 987.3}, {"model": "hrrr", "rate": "slow", "x_ft": 1092.0, "y_ft": 3363.9, "px": 2017.0, "py": 694.9}, {"model": "hrrr", "rate": "fast", "x_ft": 804.5, "y_ft": 2296.7, "px": 1931.7, "py": 1011.6}, {"model": "ecmwf", "rate": "slow", "x_ft": 783.5, "y_ft": 3336.6, "px": 1925.5, "py": 703.0}, {"model": "ecmwf", "rate": "fast", "x_ft": 585.1, "y_ft": 2278.5, "px": 1866.6, "py": 1017.0}, {"model": "icon", "rate": "slow", "x_ft": 853.6, "y_ft": 3576.3, "px": 1946.3, "py": 631.9}, {"model": "icon", "rate": "fast", "x_ft": 619.8, "y_ft": 2437.6, "px": 1876.9, "py": 969.8}, {"model": "arpege", "rate": "slow", "x_ft": 594.0, "y_ft": 3583.0, "px": 1869.3, "py": 629.9}, {"model": "arpege", "rate": "fast", "x_ft": 520.3, "y_ft": 2541.1, "px": 1847.4, "py": 939.1}, {"model": "gem", "rate": "slow", "x_ft": 958.2, "y_ft": 4068.2, "px": 1977.3, "py": 486.0}, {"model": "gem", "rate": "fast", "x_ft": 711.8, "y_ft": 2771.3, "px": 1904.2, "py": 870.8}]}, {"altitude": 10000, "core_hull_px": [[2117.7, 196.5], [1799.7, 437.3], [1814.5, 818.9], [1972.7, 823.7], [2032.7, 813.3], [2143.2, 447.1]], "buffer_hull_px": [[1276.6, 437.3], [1291.3, 818.9], [1361.4, 1080.5], [1552.9, 1271.9], [1814.5, 1342.0], [1972.7, 1346.9], [2032.7, 1336.5], [2294.2, 1266.4], [2485.7, 1074.9], [2596.3, 708.7], [2666.4, 447.1], [2640.9, 196.5], [2570.8, -65.0], [2379.3, -256.5], [2117.7, -326.6], [1856.2, -256.5], [1538.1, -15.7], [1346.6, 175.7]], "buffer_radius_ft": 1763.3, "points": [{"model": "gfs", "rate": "slow", "x_ft": 359.7, "y_ft": 4232.2, "px": 1799.7, "py": 437.3}, {"model": "gfs", "rate": "fast", "x_ft": 409.4, "y_ft": 2946.2, "px": 1814.5, "py": 818.9}, {"model": "hrrr", "rate": "slow", "x_ft": 1517.4, "y_ft": 4199.3, "px": 2143.2, "py": 447.1}, {"model": "hrrr", "rate": "fast", "x_ft": 1144.8, "y_ft": 2965.0, "px": 2032.7, "py": 813.3}, {"model": "ecmwf", "rate": "slow", "x_ft": 1230.5, "y_ft": 4150.8, "px": 2058.1, "py": 461.5}, {"model": "ecmwf", "rate": "fast", "x_ft": 942.6, "y_ft": 2929.8, "px": 1972.7, "py": 823.7}, {"model": "icon", "rate": "slow", "x_ft": 1280.8, "y_ft": 4448.6, "px": 2073.0, "py": 373.1}, {"model": "icon", "rate": "fast", "x_ft": 961.6, "y_ft": 3135.4, "px": 1978.3, "py": 762.7}, {"model": "arpege", "rate": "slow", "x_ft": 1050.2, "y_ft": 4408.3, "px": 2004.6, "py": 385.1}, {"model": "arpege", "rate": "fast", "x_ft": 885.3, "y_ft": 3201.4, "px": 1955.7, "py": 743.2}, {"model": "gem", "rate": "slow", "x_ft": 1431.6, "y_ft": 5043.7, "px": 2117.7, "py": 196.5}, {"model": "gem", "rate": "fast", "x_ft": 1090.5, "y_ft": 3551.7, "px": 2016.5, "py": 639.2}]}], "15_single": [{"altitude": 1000, "core_hull_px": [[1762.5, 1091.3], [1552.1, 1141.0], [1622.6, 1417.0], [1666.1, 1484.0], [1737.2, 1446.8], [1781.4, 1200.6]], "buffer_hull_px": [[1499.8, 1141.0], [1570.2, 1417.0], [1577.3, 1443.2], [1620.8, 1510.1], [1639.9, 1529.3], [1666.1, 1536.3], [1692.2, 1529.3], [1763.3, 1492.1], [1782.5, 1473.0], [1789.5, 1446.8], [1833.7, 1200.6], [1814.8, 1091.3], [1807.8, 1065.1], [1788.6, 1046.0], [1762.5, 1039.0], [1552.1, 1088.7], [1526.0, 1095.7], [1506.8, 1114.8]], "buffer_radius_ft": 176.3, "points": [{"model": "gfs", "rate": "10fps", "x_ft": -474.8, "y_ft": 1860.5, "px": 1552.1, "py": 1141.0}, {"model": "gfs", "rate": "20fps", "x_ft": -237.4, "y_ft": 930.2, "px": 1622.6, "py": 1417.0}, {"model": "hrrr", "rate": "10fps", "x_ft": 297.9, "y_ft": 1659.6, "px": 1781.4, "py": 1200.6}, {"model": "hrrr", "rate": "20fps", "x_ft": 148.9, "y_ft": 829.8, "px": 1737.2, "py": 1446.8}, {"model": "ecmwf", "rate": "10fps", "x_ft": 184.3, "y_ft": 1648.2, "px": 1747.7, "py": 1204.0}, {"model": "ecmwf", "rate": "20fps", "x_ft": 92.2, "y_ft": 824.1, "px": 1720.3, "py": 1448.5}, {"model": "icon", "rate": "10fps", "x_ft": 271.3, "y_ft": 1795.0, "px": 1773.5, "py": 1160.4}, {"model": "icon", "rate": "20fps", "x_ft": 135.6, "y_ft": 897.5, "px": 1733.2, "py": 1426.7}, {"model": "arpege", "rate": "10fps", "x_ft": -181.6, "y_ft": 1409.2, "px": 1639.1, "py": 1274.9}, {"model": "arpege", "rate": "20fps", "x_ft": -90.8, "y_ft": 704.6, "px": 1666.1, "py": 1484.0}, {"model": "gem", "rate": "10fps", "x_ft": 234.1, "y_ft": 2028.1, "px": 1762.5, "py": 1091.3}, {"model": "gem", "rate": "20fps", "x_ft": 117.1, "y_ft": 1014.0, "px": 1727.7, "py": 1392.1}]}, {"altitude": 3200, "core_hull_px": [[1894.7, 821.4], [2096.5, -50.3], [2050.5, -315.1], [1991.3, -394.1], [1632.8, -314.1], [1662.9, 689.4], [1681.3, 750.5], [1842.0, 810.3]], "buffer_hull_px": [[1465.4, -314.1], [1495.5, 689.4], [1517.9, 773.1], [1536.3, 834.2], [1597.6, 895.4], [1758.3, 955.3], [1842.0, 977.7], [1894.7, 988.8], [1978.4, 966.3], [2039.7, 905.1], [2062.2, 821.4], [2263.9, -50.3], [2217.9, -315.1], [2195.5, -398.8], [2136.3, -477.8], [2075.0, -539.0], [1991.3, -561.5], [1632.8, -481.5], [1549.1, -459.1], [1487.8, -397.8]], "buffer_radius_ft": 564.2, "points": [{"model": "gfs", "rate": "10fps", "x_ft": -202.9, "y_ft": 6764.8, "px": 1632.8, "py": -314.1}, {"model": "gfs", "rate": "20fps", "x_ft": -101.5, "y_ft": 3382.4, "px": 1662.9, "py": 689.4}, {"model": "hrrr", "rate": "10fps", "x_ft": 1359.9, "y_ft": 5875.6, "px": 2096.5, "py": -50.3}, {"model": "hrrr", "rate": "20fps", "x_ft": 680.0, "y_ft": 2937.8, "px": 1894.7, "py": 821.4}, {"model": "ecmwf", "rate": "10fps", "x_ft": 1004.7, "y_ft": 5949.9, "px": 1991.1, "py": -72.3}, {"model": "ecmwf", "rate": "20fps", "x_ft": 502.4, "y_ft": 2975.0, "px": 1842.0, "py": 810.3}, {"model": "icon", "rate": "10fps", "x_ft": 1204.9, "y_ft": 6768.1, "px": 2050.5, "py": -315.1}, {"model": "icon", "rate": "20fps", "x_ft": 602.5, "y_ft": 3384.1, "px": 1871.8, "py": 689.0}, {"model": "arpege", "rate": "10fps", "x_ft": -79.0, "y_ft": 6353.5, "px": 1669.5, "py": -192.1}, {"model": "arpege", "rate": "20fps", "x_ft": -39.5, "y_ft": 3176.7, "px": 1681.3, "py": 750.5}, {"model": "gem", "rate": "10fps", "x_ft": 1005.5, "y_ft": 7034.2, "px": 1991.3, "py": -394.1}, {"model": "gem", "rate": "20fps", "x_ft": 502.7, "y_ft": 3517.1, "px": 1842.2, "py": 649.5}]}, {"altitude": 5500, "core_hull_px": [[2787.1, -1675.9], [2589.4, -2347.4], [2284.2, -2308.1], [2091.6, -1944.0], [1892.3, -125.5], [2085.5, 7.7], [2240.1, 8.5]], "buffer_hull_px": [[3036.3, -1532.1], [3074.9, -1675.9], [3036.3, -1819.8], [2838.6, -2491.3], [2733.3, -2596.6], [2589.4, -2635.1], [2284.2, -2595.8], [2140.3, -2557.3], [2035.0, -2451.9], [1842.4, -2087.9], [1803.8, -1944.0], [1604.5, -125.5], [1643.1, 18.4], [1748.4, 123.7], [1941.6, 256.9], [2085.5, 295.4], [2240.1, 296.3], [2383.9, 257.7], [2489.2, 152.4]], "buffer_radius_ft": 969.8, "points": [{"model": "gfs", "rate": "10fps", "x_ft": 1343.4, "y_ft": 12258.3, "px": 2091.6, "py": -1944.0}, {"model": "gfs", "rate": "20fps", "x_ft": 671.7, "y_ft": 6129.1, "px": 1892.3, "py": -125.5}, {"model": "hrrr", "rate": "10fps", "x_ft": 3687.6, "y_ft": 11354.7, "px": 2787.1, "py": -1675.9}, {"model": "hrrr", "rate": "20fps", "x_ft": 1843.8, "y_ft": 5677.3, "px": 2240.1, "py": 8.5}, {"model": "ecmwf", "rate": "10fps", "x_ft": 2645.8, "y_ft": 11360.4, "px": 2478.0, "py": -1677.6}, {"model": "ecmwf", "rate": "20fps", "x_ft": 1322.9, "y_ft": 5680.2, "px": 2085.5, "py": 7.7}, {"model": "icon", "rate": "10fps", "x_ft": 2846.1, "y_ft": 12478.5, "px": 2537.4, "py": -2009.4}, {"model": "icon", "rate": "20fps", "x_ft": 1423.0, "y_ft": 6239.3, "px": 2115.2, "py": -158.2}, {"model": "arpege", "rate": "10fps", "x_ft": 1992.7, "y_ft": 13485.3, "px": 2284.2, "py": -2308.1}, {"model": "arpege", "rate": "20fps", "x_ft": 996.3, "y_ft": 6742.6, "px": 1988.6, "py": -307.5}, {"model": "gem", "rate": "10fps", "x_ft": 3021.2, "y_ft": 13617.9, "px": 2589.4, "py": -2347.4}, {"model": "gem", "rate": "20fps", "x_ft": 1510.6, "y_ft": 6808.9, "px": 2141.2, "py": -327.2}]}, {"altitude": 7800, "core_hull_px": [[3806.6, -3560.8], [3588.2, -4617.8], [3415.3, -4559.4], [2735.3, -3625.2], [2214.1, -966.1], [2478.3, -914.0], [2749.8, -933.9]], "buffer_hull_px": [[4160.0, -3356.7], [4214.7, -3560.8], [3996.2, -4617.8], [3941.6, -4821.9], [3792.2, -4971.2], [3588.2, -5025.9], [3384.1, -4971.2], [3211.3, -4912.8], [3062.0, -4763.5], [2381.9, -3829.3], [2327.2, -3625.2], [1806.1, -966.1], [1860.7, -762.1], [2010.1, -612.7], [2214.1, -558.1], [2478.3, -505.9], [2749.8, -525.8], [2953.8, -580.5], [3103.2, -729.8]], "buffer_radius_ft": 1375.4, "points": [{"model": "gfs", "rate": "10fps", "x_ft": 3512.8, "y_ft": 17924.7, "px": 2735.3, "py": -3625.2}, {"model": "gfs", "rate": "20fps", "x_ft": 1756.4, "y_ft": 8962.4, "px": 2214.1, "py": -966.1}, {"model": "hrrr", "rate": "10fps", "x_ft": 7123.7, "y_ft": 17707.4, "px": 3806.6, "py": -3560.8}, {"model": "hrrr", "rate": "20fps", "x_ft": 3561.8, "y_ft": 8853.7, "px": 2749.8, "py": -933.9}, {"model": "ecmwf", "rate": "10fps", "x_ft": 5293.5, "y_ft": 17573.4, "px": 3263.6, "py": -3521.0}, {"model": "ecmwf", "rate": "20fps", "x_ft": 2646.8, "y_ft": 8786.7, "px": 2478.3, "py": -914.0}, {"model": "icon", "rate": "10fps", "x_ft": 5356.9, "y_ft": 18730.2, "px": 3282.4, "py": -3864.2}, {"model": "icon", "rate": "20fps", "x_ft": 2678.5, "y_ft": 9365.1, "px": 2487.7, "py": -1085.6}, {"model": "arpege", "rate": "10fps", "x_ft": 5805.0, "y_ft": 21073.4, "px": 3415.3, "py": -4559.4}, {"model": "arpege", "rate": "20fps", "x_ft": 2902.5, "y_ft": 10536.7, "px": 2554.2, "py": -1433.2}, {"model": "gem", "rate": "10fps", "x_ft": 6387.5, "y_ft": 21270.1, "px": 3588.2, "py": -4617.8}, {"model": "gem", "rate": "20fps", "x_ft": 3193.8, "y_ft": 10635.1, "px": 2640.6, "py": -1462.4}]}, {"altitude": 10000, "core_hull_px": [[4816.3, -5543.6], [4711.8, -6933.4], [3388.8, -5309.4], [2540.9, -1808.2], [3008.8, -1880.3], [3254.6, -1925.3]], "buffer_hull_px": [[5269.4, -5282.0], [5339.5, -5543.6], [5234.9, -6933.4], [5164.9, -7195.0], [4973.4, -7386.5], [4711.8, -7456.6], [4450.2, -7386.5], [4258.7, -7195.0], [2935.8, -5570.9], [2865.7, -5309.4], [2017.8, -1808.2], [2087.8, -1546.6], [2279.3, -1355.1], [2540.9, -1285.0], [3008.8, -1357.1], [3254.6, -1402.1], [3516.2, -1472.2], [3707.7, -1663.7]], "buffer_radius_ft": 1763.3, "points": [{"model": "gfs", "rate": "10fps", "x_ft": 5715.6, "y_ft": 23600.9, "px": 3388.8, "py": -5309.4}, {"model": "gfs", "rate": "20fps", "x_ft": 2857.8, "y_ft": 11800.5, "px": 2540.9, "py": -1808.2}, {"model": "hrrr", "rate": "10fps", "x_ft": 10526.8, "y_ft": 24390.3, "px": 4816.3, "py": -5543.6}, {"model": "hrrr", "rate": "20fps", "x_ft": 5263.4, "y_ft": 12195.2, "px": 3254.6, "py": -1925.3}, {"model": "ecmwf", "rate": "10fps", "x_ft": 8869.4, "y_ft": 24086.8, "px": 4324.5, "py": -5453.5}, {"model": "ecmwf", "rate": "20fps", "x_ft": 4434.7, "y_ft": 12043.4, "px": 3008.8, "py": -1880.3}, {"model": "icon", "rate": "10fps", "x_ft": 8774.7, "y_ft": 25708.4, "px": 4296.5, "py": -5934.6}, {"model": "icon", "rate": "20fps", "x_ft": 4387.4, "y_ft": 12854.2, "px": 2994.7, "py": -2120.8}, {"model": "arpege", "rate": "10fps", "x_ft": 9454.3, "y_ft": 27676.0, "px": 4498.1, "py": -6518.4}, {"model": "arpege", "rate": "20fps", "x_ft": 4727.2, "y_ft": 13838.0, "px": 3095.5, "py": -2412.7}, {"model": "gem", "rate": "10fps", "x_ft": 10174.6, "y_ft": 29074.6, "px": 4711.8, "py": -6933.4}, {"model": "gem", "rate": "20fps", "x_ft": 5087.3, "y_ft": 14537.3, "px": 3202.4, "py": -2620.2}]}]}, "base_view_box": [-3322.4, -9601.7, 13067.7, 13067.7]}