{"target_date": "2026-07-18", "captures": ["2026-07-17"], "points_by_key": {"9_dual_fast_1000": [{"capture_date": "2026-07-17", "model": "gfs", "x_ft": 267.1, "y_ft": 1106.0}, {"capture_date": "2026-07-17", "model": "hrrr", "x_ft": 485.5, "y_ft": 981.9}, {"capture_date": "2026-07-17", "model": "ecmwf", "x_ft": 296.0, "y_ft": 744.7}, {"capture_date": "2026-07-17", "model": "icon", "x_ft": 282.9, "y_ft": 861.2}, {"capture_date": "2026-07-17", "model": "arpege", "x_ft": -82.8, "y_ft": 768.0}, {"capture_date": "2026-07-17", "model": "gem", "x_ft": 306.1, "y_ft": 909.1}], "9_dual_fast_3000": [{"capture_date": "2026-07-17", "model": "gfs", "x_ft": 619.1, "y_ft": 1815.2}, {"capture_date": "2026-07-17", "model": "hrrr", "x_ft": 1032.3, "y_ft": 1679.9}, {"capture_date": "2026-07-17", "model": "ecmwf", "x_ft": 448.8, "y_ft": 1154.3}, {"capture_date": "2026-07-17", "model": "icon", "x_ft": 794.9, "y_ft": 1478.0}, {"capture_date": "2026-07-17", "model": "arpege", "x_ft": 204.3, "y_ft": 1391.2}, {"capture_date": "2026-07-17", "model": "gem", "x_ft": 678.9, "y_ft": 1510.9}], "9_dual_fast_5000": [{"capture_date": "2026-07-17", "model": "gfs", "x_ft": 1095.1, "y_ft": 2518.7}, {"capture_date": "2026-07-17", "model": "hrrr", "x_ft": 1703.2, "y_ft": 2273.7}, {"capture_date": "2026-07-17", "model": "ecmwf", "x_ft": 613.7, "y_ft": 1634.4}, {"capture_date": "2026-07-17", "model": "icon", "x_ft": 1525.9, "y_ft": 2042.9}, {"capture_date": "2026-07-17", "model": "arpege", "x_ft": 805.8, "y_ft": 1969.3}, {"capture_date": "2026-07-17", "model": "gem", "x_ft": 1289.9, "y_ft": 2043.8}], "9_dual_fast_7000": [{"capture_date": "2026-07-17", "model": "gfs", "x_ft": 1526.4, "y_ft": 3158.3}, {"capture_date": "2026-07-17", "model": "hrrr", "x_ft": 2227.3, "y_ft": 2699.6}, {"capture_date": "2026-07-17", "model": "ecmwf", "x_ft": 786.9, "y_ft": 2186.0}, {"capture_date": "2026-07-17", "model": "icon", "x_ft": 2218.2, "y_ft": 2548.2}, {"capture_date": "2026-07-17", "model": "arpege", "x_ft": 1478.2, "y_ft": 2441.4}, {"capture_date": "2026-07-17", "model": "gem", "x_ft": 1961.0, "y_ft": 2444.6}], "9_dual_fast_9000": [{"capture_date": "2026-07-17", "model": "gfs", "x_ft": 1716.7, "y_ft": 3809.9}, {"capture_date": "2026-07-17", "model": "hrrr", "x_ft": 2406.6, "y_ft": 3099.2}, {"capture_date": "2026-07-17", "model": "ecmwf", "x_ft": 964.9, "y_ft": 2809.7}, {"capture_date": "2026-07-17", "model": "icon", "x_ft": 2623.9, "y_ft": 3193.8}, {"capture_date": "2026-07-17", "model": "arpege", "x_ft": 1918.5, "y_ft": 3026.0}, {"capture_date": "2026-07-17", "model": "gem", "x_ft": 2358.9, "y_ft": 2947.4}], "9_dual_slow_1000": [{"capture_date": "2026-07-17", "model": "gfs", "x_ft": 520.5, "y_ft": 2167.6}, {"capture_date": "2026-07-17", "model": "hrrr", "x_ft": 947.5, "y_ft": 1922.4}, {"capture_date": "2026-07-17", "model": "ecmwf", "x_ft": 581.1, "y_ft": 1461.6}, {"capture_date": "2026-07-17", "model": "icon", "x_ft": 549.0, "y_ft": 1684.8}, {"capture_date": "2026-07-17", "model": "arpege", "x_ft": -167.0, "y_ft": 1500.8}, {"capture_date": "2026-07-17", "model": "gem", "x_ft": 597.0, "y_ft": 1781.1}], "9_dual_slow_3000": [{"capture_date": "2026-07-17", "model": "gfs", "x_ft": 960.4, "y_ft": 3054.0}, {"capture_date": "2026-07-17", "model": "hrrr", "x_ft": 1630.9, "y_ft": 2794.7}, {"capture_date": "2026-07-17", "model": "ecmwf", "x_ft": 772.1, "y_ft": 1973.5}, {"capture_date": "2026-07-17", "model": "icon", "x_ft": 1188.9, "y_ft": 2455.8}, {"capture_date": "2026-07-17", "model": "arpege", "x_ft": 191.9, "y_ft": 2279.7}, {"capture_date": "2026-07-17", "model": "gem", "x_ft": 1063.0, "y_ft": 2533.3}], "9_dual_slow_5000": [{"capture_date": "2026-07-17", "model": "gfs", "x_ft": 1555.4, "y_ft": 3933.4}, {"capture_date": "2026-07-17", "model": "hrrr", "x_ft": 2469.6, "y_ft": 3537.1}, {"capture_date": "2026-07-17", "model": "ecmwf", "x_ft": 978.2, "y_ft": 2573.7}, {"capture_date": "2026-07-17", "model": "icon", "x_ft": 2102.7, "y_ft": 3162.0}, {"capture_date": "2026-07-17", "model": "arpege", "x_ft": 943.8, "y_ft": 3002.4}, {"capture_date": "2026-07-17", "model": "gem", "x_ft": 1826.7, "y_ft": 3199.4}], "9_dual_slow_7000": [{"capture_date": "2026-07-17", "model": "gfs", "x_ft": 2094.5, "y_ft": 4733.0}, {"capture_date": "2026-07-17", "model": "hrrr", "x_ft": 3124.7, "y_ft": 4069.4}, {"capture_date": "2026-07-17", "model": "ecmwf", "x_ft": 1194.8, "y_ft": 3263.1}, {"capture_date": "2026-07-17", "model": "icon", "x_ft": 2968.1, "y_ft": 3793.6}, {"capture_date": "2026-07-17", "model": "arpege", "x_ft": 1784.2, "y_ft": 3592.5}, {"capture_date": "2026-07-17", "model": "gem", "x_ft": 2665.6, "y_ft": 3700.4}], "9_dual_slow_9000": [{"capture_date": "2026-07-17", "model": "gfs", "x_ft": 2332.4, "y_ft": 5547.4}, {"capture_date": "2026-07-17", "model": "hrrr", "x_ft": 3348.8, "y_ft": 4568.9}, {"capture_date": "2026-07-17", "model": "ecmwf", "x_ft": 1417.2, "y_ft": 4042.8}, {"capture_date": "2026-07-17", "model": "icon", "x_ft": 3475.2, "y_ft": 4600.6}, {"capture_date": "2026-07-17", "model": "arpege", "x_ft": 2334.7, "y_ft": 4323.2}, {"capture_date": "2026-07-17", "model": "gem", "x_ft": 3163.0, "y_ft": 4329.0}], "9_single_10fps_1000": [{"capture_date": "2026-07-17", "model": "gfs", "x_ft": 681.8, "y_ft": 2686.1}, {"capture_date": "2026-07-17", "model": "hrrr", "x_ft": 1222.7, "y_ft": 2407.0}, {"capture_date": "2026-07-17", "model": "ecmwf", "x_ft": 707.8, "y_ft": 1786.3}, {"capture_date": "2026-07-17", "model": "icon", "x_ft": 745.5, "y_ft": 2123.2}, {"capture_date": "2026-07-17", "model": "arpege", "x_ft": -150.1, "y_ft": 1912.3}, {"capture_date": "2026-07-17", "model": "gem", "x_ft": 774.7, "y_ft": 2214.7}], "9_single_10fps_3000": [{"capture_date": "2026-07-17", "model": "gfs", "x_ft": 4201.1, "y_ft": 9777.9}, {"capture_date": "2026-07-17", "model": "hrrr", "x_ft": 6690.1, "y_ft": 9386.1}, {"capture_date": "2026-07-17", "model": "ecmwf", "x_ft": 2236.2, "y_ft": 5881.9}, {"capture_date": "2026-07-17", "model": "icon", "x_ft": 5865.0, "y_ft": 8290.6}, {"capture_date": "2026-07-17", "model": "arpege", "x_ft": 2720.5, "y_ft": 8144.0}, {"capture_date": "2026-07-17", "model": "gem", "x_ft": 4503.1, "y_ft": 8232.2}], "9_single_10fps_5000": [{"capture_date": "2026-07-17", "model": "gfs", "x_ft": 8961.2, "y_ft": 16812.8}, {"capture_date": "2026-07-17", "model": "hrrr", "x_ft": 13399.6, "y_ft": 15324.9}, {"capture_date": "2026-07-17", "model": "ecmwf", "x_ft": 3884.8, "y_ft": 10683.2}, {"capture_date": "2026-07-17", "model": "icon", "x_ft": 13175.4, "y_ft": 13940.5}, {"capture_date": "2026-07-17", "model": "arpege", "x_ft": 8735.8, "y_ft": 13925.4}, {"capture_date": "2026-07-17", "model": "gem", "x_ft": 10612.4, "y_ft": 13560.9}], "9_single_10fps_7000": [{"capture_date": "2026-07-17", "model": "gfs", "x_ft": 13274.2, "y_ft": 23209.4}, {"capture_date": "2026-07-17", "model": "hrrr", "x_ft": 18640.4, "y_ft": 19583.5}, {"capture_date": "2026-07-17", "model": "ecmwf", "x_ft": 5617.3, "y_ft": 16198.8}, {"capture_date": "2026-07-17", "model": "icon", "x_ft": 20098.5, "y_ft": 18993.1}, {"capture_date": "2026-07-17", "model": "arpege", "x_ft": 15459.1, "y_ft": 18645.8}, {"capture_date": "2026-07-17", "model": "gem", "x_ft": 17323.5, "y_ft": 17569.5}], "9_single_10fps_9000": [{"capture_date": "2026-07-17", "model": "gfs", "x_ft": 15177.2, "y_ft": 29724.7}, {"capture_date": "2026-07-17", "model": "hrrr", "x_ft": 20433.0, "y_ft": 23579.3}, {"capture_date": "2026-07-17", "model": "ecmwf", "x_ft": 7396.9, "y_ft": 22436.2}, {"capture_date": "2026-07-17", "model": "icon", "x_ft": 24155.6, "y_ft": 25449.3}, {"capture_date": "2026-07-17", "model": "arpege", "x_ft": 19863.0, "y_ft": 24491.7}, {"capture_date": "2026-07-17", "model": "gem", "x_ft": 21303.1, "y_ft": 22597.7}], "9_single_20fps_1000": [{"capture_date": "2026-07-17", "model": "gfs", "x_ft": 340.9, "y_ft": 1343.1}, {"capture_date": "2026-07-17", "model": "hrrr", "x_ft": 611.4, "y_ft": 1203.5}, {"capture_date": "2026-07-17", "model": "ecmwf", "x_ft": 353.9, "y_ft": 893.2}, {"capture_date": "2026-07-17", "model": "icon", "x_ft": 372.8, "y_ft": 1061.6}, {"capture_date": "2026-07-17", "model": "arpege", "x_ft": -75.0, "y_ft": 956.1}, {"capture_date": "2026-07-17", "model": "gem", "x_ft": 387.3, "y_ft": 1107.4}], "9_single_20fps_3000": [{"capture_date": "2026-07-17", "model": "gfs", "x_ft": 2100.6, "y_ft": 4888.9}, {"capture_date": "2026-07-17", "model": "hrrr", "x_ft": 3345.0, "y_ft": 4693.0}, {"capture_date": "2026-07-17", "model": "ecmwf", "x_ft": 1118.1, "y_ft": 2941.0}, {"capture_date": "2026-07-17", "model": "icon", "x_ft": 2932.5, "y_ft": 4145.3}, {"capture_date": "2026-07-17", "model": "arpege", "x_ft": 1360.2, "y_ft": 4072.0}, {"capture_date": "2026-07-17", "model": "gem", "x_ft": 2251.6, "y_ft": 4116.1}], "9_single_20fps_5000": [{"capture_date": "2026-07-17", "model": "gfs", "x_ft": 4480.6, "y_ft": 8406.4}, {"capture_date": "2026-07-17", "model": "hrrr", "x_ft": 6699.8, "y_ft": 7662.5}, {"capture_date": "2026-07-17", "model": "ecmwf", "x_ft": 1942.4, "y_ft": 5341.6}, {"capture_date": "2026-07-17", "model": "icon", "x_ft": 6587.7, "y_ft": 6970.2}, {"capture_date": "2026-07-17", "model": "arpege", "x_ft": 4367.9, "y_ft": 6962.7}, {"capture_date": "2026-07-17", "model": "gem", "x_ft": 5306.2, "y_ft": 6780.5}], "9_single_20fps_7000": [{"capture_date": "2026-07-17", "model": "gfs", "x_ft": 6637.1, "y_ft": 11604.7}, {"capture_date": "2026-07-17", "model": "hrrr", "x_ft": 9320.2, "y_ft": 9791.8}, {"capture_date": "2026-07-17", "model": "ecmwf", "x_ft": 2808.7, "y_ft": 8099.4}, {"capture_date": "2026-07-17", "model": "icon", "x_ft": 10049.2, "y_ft": 9496.6}, {"capture_date": "2026-07-17", "model": "arpege", "x_ft": 7729.6, "y_ft": 9322.9}, {"capture_date": "2026-07-17", "model": "gem", "x_ft": 8661.8, "y_ft": 8784.7}], "9_single_20fps_9000": [{"capture_date": "2026-07-17", "model": "gfs", "x_ft": 7588.6, "y_ft": 14862.3}, {"capture_date": "2026-07-17", "model": "hrrr", "x_ft": 10216.5, "y_ft": 11789.6}, {"capture_date": "2026-07-17", "model": "ecmwf", "x_ft": 3698.5, "y_ft": 11218.1}, {"capture_date": "2026-07-17", "model": "icon", "x_ft": 12077.8, "y_ft": 12724.6}, {"capture_date": "2026-07-17", "model": "arpege", "x_ft": 9931.5, "y_ft": 12245.9}, {"capture_date": "2026-07-17", "model": "gem", "x_ft": 10651.6, "y_ft": 11298.9}], "11_dual_fast_1000": [{"capture_date": "2026-07-17", "model": "gfs", "x_ft": 435.8, "y_ft": 986.6}, {"capture_date": "2026-07-17", "model": "hrrr", "x_ft": 473.2, "y_ft": 883.3}, {"capture_date": "2026-07-17", "model": "ecmwf", "x_ft": 430.3, "y_ft": 789.8}, {"capture_date": "2026-07-17", "model": "icon", "x_ft": 418.2, "y_ft": 758.7}, {"capture_date": "2026-07-17", "model": "arpege", "x_ft": 120.3, "y_ft": 719.8}, {"capture_date": "2026-07-17", "model": "gem", "x_ft": 492.4, "y_ft": 734.4}], "11_dual_fast_3000": [{"capture_date": "2026-07-17", "model": "gfs", "x_ft": 749.8, "y_ft": 1522.7}, {"capture_date": "2026-07-17", "model": "hrrr", "x_ft": 814.2, "y_ft": 1415.2}, {"capture_date": "2026-07-17", "model": "ecmwf", "x_ft": 654.7, "y_ft": 1229.7}, {"capture_date": "2026-07-17", "model": "icon", "x_ft": 755.2, "y_ft": 1227.1}, {"capture_date": "2026-07-17", "model": "arpege", "x_ft": 361.8, "y_ft": 1217.2}, {"capture_date": "2026-07-17", "model": "gem", "x_ft": 833.4, "y_ft": 1185.5}], "11_dual_fast_5000": [{"capture_date": "2026-07-17", "model": "gfs", "x_ft": 1100.4, "y_ft": 2111.6}, {"capture_date": "2026-07-17", "model": "hrrr", "x_ft": 1255.6, "y_ft": 1899.3}, {"capture_date": "2026-07-17", "model": "ecmwf", "x_ft": 899.3, "y_ft": 1752.4}, {"capture_date": "2026-07-17", "model": "icon", "x_ft": 1175.3, "y_ft": 1647.0}, {"capture_date": "2026-07-17", "model": "arpege", "x_ft": 846.3, "y_ft": 1628.2}, {"capture_date": "2026-07-17", "model": "gem", "x_ft": 1291.6, "y_ft": 1641.1}], "11_dual_fast_7000": [{"capture_date": "2026-07-17", "model": "gfs", "x_ft": 1414.7, "y_ft": 2740.7}, {"capture_date": "2026-07-17", "model": "hrrr", "x_ft": 1697.2, "y_ft": 2313.9}, {"capture_date": "2026-07-17", "model": "ecmwf", "x_ft": 1158.6, "y_ft": 2359.5}, {"capture_date": "2026-07-17", "model": "icon", "x_ft": 1610.1, "y_ft": 2013.7}, {"capture_date": "2026-07-17", "model": "arpege", "x_ft": 1443.2, "y_ft": 1920.4}, {"capture_date": "2026-07-17", "model": "gem", "x_ft": 1802.0, "y_ft": 2083.1}], "11_dual_fast_9000": [{"capture_date": "2026-07-17", "model": "gfs", "x_ft": 1630.1, "y_ft": 3390.5}, {"capture_date": "2026-07-17", "model": "hrrr", "x_ft": 1921.0, "y_ft": 2867.0}, {"capture_date": "2026-07-17", "model": "ecmwf", "x_ft": 1427.3, "y_ft": 3052.7}, {"capture_date": "2026-07-17", "model": "icon", "x_ft": 2030.3, "y_ft": 2615.1}, {"capture_date": "2026-07-17", "model": "arpege", "x_ft": 1868.8, "y_ft": 2589.8}, {"capture_date": "2026-07-17", "model": "gem", "x_ft": 2150.4, "y_ft": 2684.8}], "11_dual_slow_1000": [{"capture_date": "2026-07-17", "model": "gfs", "x_ft": 853.7, "y_ft": 1936.2}, {"capture_date": "2026-07-17", "model": "hrrr", "x_ft": 927.0, "y_ft": 1732.3}, {"capture_date": "2026-07-17", "model": "ecmwf", "x_ft": 844.7, "y_ft": 1550.0}, {"capture_date": "2026-07-17", "model": "icon", "x_ft": 818.6, "y_ft": 1487.5}, {"capture_date": "2026-07-17", "model": "arpege", "x_ft": 233.0, "y_ft": 1409.6}, {"capture_date": "2026-07-17", "model": "gem", "x_ft": 964.9, "y_ft": 1440.1}], "11_dual_slow_3000": [{"capture_date": "2026-07-17", "model": "gfs", "x_ft": 1246.3, "y_ft": 2606.4}, {"capture_date": "2026-07-17", "model": "hrrr", "x_ft": 1353.2, "y_ft": 2397.2}, {"capture_date": "2026-07-17", "model": "ecmwf", "x_ft": 1125.2, "y_ft": 2099.9}, {"capture_date": "2026-07-17", "model": "icon", "x_ft": 1239.9, "y_ft": 2073.0}, {"capture_date": "2026-07-17", "model": "arpege", "x_ft": 535.0, "y_ft": 2031.3}, {"capture_date": "2026-07-17", "model": "gem", "x_ft": 1391.2, "y_ft": 2003.9}], "11_dual_slow_5000": [{"capture_date": "2026-07-17", "model": "gfs", "x_ft": 1684.5, "y_ft": 3342.5}, {"capture_date": "2026-07-17", "model": "hrrr", "x_ft": 1905.1, "y_ft": 3002.2}, {"capture_date": "2026-07-17", "model": "ecmwf", "x_ft": 1430.9, "y_ft": 2753.2}, {"capture_date": "2026-07-17", "model": "icon", "x_ft": 1765.0, "y_ft": 2597.9}, {"capture_date": "2026-07-17", "model": "arpege", "x_ft": 1140.5, "y_ft": 2545.1}, {"capture_date": "2026-07-17", "model": "gem", "x_ft": 1964.0, "y_ft": 2573.4}], "11_dual_slow_7000": [{"capture_date": "2026-07-17", "model": "gfs", "x_ft": 2077.3, "y_ft": 4128.9}, {"capture_date": "2026-07-17", "model": "hrrr", "x_ft": 2457.1, "y_ft": 3520.6}, {"capture_date": "2026-07-17", "model": "ecmwf", "x_ft": 1755.2, "y_ft": 3512.1}, {"capture_date": "2026-07-17", "model": "icon", "x_ft": 2308.5, "y_ft": 3056.2}, {"capture_date": "2026-07-17", "model": "arpege", "x_ft": 1886.8, "y_ft": 2910.3}, {"capture_date": "2026-07-17", "model": "gem", "x_ft": 2602.0, "y_ft": 3126.0}], "11_dual_slow_9000": [{"capture_date": "2026-07-17", "model": "gfs", "x_ft": 2346.6, "y_ft": 4941.2}, {"capture_date": "2026-07-17", "model": "hrrr", "x_ft": 2736.8, "y_ft": 4211.9}, {"capture_date": "2026-07-17", "model": "ecmwf", "x_ft": 2091.0, "y_ft": 4378.5}, {"capture_date": "2026-07-17", "model": "icon", "x_ft": 2833.7, "y_ft": 3808.0}, {"capture_date": "2026-07-17", "model": "arpege", "x_ft": 2418.7, "y_ft": 3747.0}, {"capture_date": "2026-07-17", "model": "gem", "x_ft": 3037.4, "y_ft": 3878.1}], "11_single_10fps_1000": [{"capture_date": "2026-07-17", "model": "gfs", "x_ft": 1062.1, "y_ft": 2367.1}, {"capture_date": "2026-07-17", "model": "hrrr", "x_ft": 1153.0, "y_ft": 2132.9}, {"capture_date": "2026-07-17", "model": "ecmwf", "x_ft": 1029.5, "y_ft": 1895.8}, {"capture_date": "2026-07-17", "model": "icon", "x_ft": 1026.7, "y_ft": 1836.4}, {"capture_date": "2026-07-17", "model": "arpege", "x_ft": 320.4, "y_ft": 1759.6}, {"capture_date": "2026-07-17", "model": "gem", "x_ft": 1197.1, "y_ft": 1774.9}], "11_single_10fps_3000": [{"capture_date": "2026-07-17", "model": "gfs", "x_ft": 4202.8, "y_ft": 7728.4}, {"capture_date": "2026-07-17", "model": "hrrr", "x_ft": 4562.7, "y_ft": 7451.7}, {"capture_date": "2026-07-17", "model": "ecmwf", "x_ft": 3273.4, "y_ft": 6295.0}, {"capture_date": "2026-07-17", "model": "icon", "x_ft": 4396.8, "y_ft": 6520.3}, {"capture_date": "2026-07-17", "model": "arpege", "x_ft": 2736.1, "y_ft": 6733.7}, {"capture_date": "2026-07-17", "model": "gem", "x_ft": 4607.4, "y_ft": 6285.9}], "11_single_10fps_5000": [{"capture_date": "2026-07-17", "model": "gfs", "x_ft": 7708.4, "y_ft": 13617.6}, {"capture_date": "2026-07-17", "model": "hrrr", "x_ft": 8977.4, "y_ft": 12292.3}, {"capture_date": "2026-07-17", "model": "ecmwf", "x_ft": 5719.3, "y_ft": 11521.3}, {"capture_date": "2026-07-17", "model": "icon", "x_ft": 8597.7, "y_ft": 10719.3}, {"capture_date": "2026-07-17", "model": "arpege", "x_ft": 7580.6, "y_ft": 10844.1}, {"capture_date": "2026-07-17", "model": "gem", "x_ft": 9189.3, "y_ft": 10841.9}], "11_single_10fps_7000": [{"capture_date": "2026-07-17", "model": "gfs", "x_ft": 10851.2, "y_ft": 19908.2}, {"capture_date": "2026-07-17", "model": "hrrr", "x_ft": 13393.3, "y_ft": 16439.1}, {"capture_date": "2026-07-17", "model": "ecmwf", "x_ft": 8313.2, "y_ft": 17592.6}, {"capture_date": "2026-07-17", "model": "icon", "x_ft": 12945.8, "y_ft": 14385.8}, {"capture_date": "2026-07-17", "model": "arpege", "x_ft": 13550.4, "y_ft": 13765.5}, {"capture_date": "2026-07-17", "model": "gem", "x_ft": 14293.3, "y_ft": 15262.0}], "11_single_10fps_9000": [{"capture_date": "2026-07-17", "model": "gfs", "x_ft": 13005.8, "y_ft": 26406.5}, {"capture_date": "2026-07-17", "model": "hrrr", "x_ft": 15631.5, "y_ft": 21969.4}, {"capture_date": "2026-07-17", "model": "ecmwf", "x_ft": 11000.0, "y_ft": 24524.3}, {"capture_date": "2026-07-17", "model": "icon", "x_ft": 17147.4, "y_ft": 20399.9}, {"capture_date": "2026-07-17", "model": "arpege", "x_ft": 17806.1, "y_ft": 20459.3}, {"capture_date": "2026-07-17", "model": "gem", "x_ft": 17777.1, "y_ft": 21279.1}], "11_single_20fps_1000": [{"capture_date": "2026-07-17", "model": "gfs", "x_ft": 531.0, "y_ft": 1183.6}, {"capture_date": "2026-07-17", "model": "hrrr", "x_ft": 576.5, "y_ft": 1066.4}, {"capture_date": "2026-07-17", "model": "ecmwf", "x_ft": 514.8, "y_ft": 947.9}, {"capture_date": "2026-07-17", "model": "icon", "x_ft": 513.3, "y_ft": 918.2}, {"capture_date": "2026-07-17", "model": "arpege", "x_ft": 160.2, "y_ft": 879.8}, {"capture_date": "2026-07-17", "model": "gem", "x_ft": 598.6, "y_ft": 887.5}], "11_single_20fps_3000": [{"capture_date": "2026-07-17", "model": "gfs", "x_ft": 2101.4, "y_ft": 3864.2}, {"capture_date": "2026-07-17", "model": "hrrr", "x_ft": 2281.3, "y_ft": 3725.9}, {"capture_date": "2026-07-17", "model": "ecmwf", "x_ft": 1636.7, "y_ft": 3147.5}, {"capture_date": "2026-07-17", "model": "icon", "x_ft": 2198.4, "y_ft": 3260.1}, {"capture_date": "2026-07-17", "model": "arpege", "x_ft": 1368.1, "y_ft": 3366.8}, {"capture_date": "2026-07-17", "model": "gem", "x_ft": 2303.7, "y_ft": 3143.0}], "11_single_20fps_5000": [{"capture_date": "2026-07-17", "model": "gfs", "x_ft": 3854.2, "y_ft": 6808.8}, {"capture_date": "2026-07-17", "model": "hrrr", "x_ft": 4488.7, "y_ft": 6146.2}, {"capture_date": "2026-07-17", "model": "ecmwf", "x_ft": 2859.6, "y_ft": 5760.6}, {"capture_date": "2026-07-17", "model": "icon", "x_ft": 4298.8, "y_ft": 5359.7}, {"capture_date": "2026-07-17", "model": "arpege", "x_ft": 3790.3, "y_ft": 5422.0}, {"capture_date": "2026-07-17", "model": "gem", "x_ft": 4594.7, "y_ft": 5421.0}], "11_single_20fps_7000": [{"capture_date": "2026-07-17", "model": "gfs", "x_ft": 5425.6, "y_ft": 9954.1}, {"capture_date": "2026-07-17", "model": "hrrr", "x_ft": 6696.6, "y_ft": 8219.5}, {"capture_date": "2026-07-17", "model": "ecmwf", "x_ft": 4156.6, "y_ft": 8796.3}, {"capture_date": "2026-07-17", "model": "icon", "x_ft": 6472.9, "y_ft": 7192.9}, {"capture_date": "2026-07-17", "model": "arpege", "x_ft": 6775.2, "y_ft": 6882.7}, {"capture_date": "2026-07-17", "model": "gem", "x_ft": 7146.6, "y_ft": 7631.0}], "11_single_20fps_9000": [{"capture_date": "2026-07-17", "model": "gfs", "x_ft": 6502.9, "y_ft": 13203.2}, {"capture_date": "2026-07-17", "model": "hrrr", "x_ft": 7815.8, "y_ft": 10984.7}, {"capture_date": "2026-07-17", "model": "ecmwf", "x_ft": 5500.0, "y_ft": 12262.1}, {"capture_date": "2026-07-17", "model": "icon", "x_ft": 8573.7, "y_ft": 10199.9}, {"capture_date": "2026-07-17", "model": "arpege", "x_ft": 8903.1, "y_ft": 10229.6}, {"capture_date": "2026-07-17", "model": "gem", "x_ft": 8888.6, "y_ft": 10639.5}], "13_dual_fast_1000": [{"capture_date": "2026-07-17", "model": "gfs", "x_ft": 326.2, "y_ft": 965.6}, {"capture_date": "2026-07-17", "model": "hrrr", "x_ft": 188.7, "y_ft": 942.1}, {"capture_date": "2026-07-17", "model": "ecmwf", "x_ft": 197.4, "y_ft": 691.3}, {"capture_date": "2026-07-17", "model": "icon", "x_ft": 169.0, "y_ft": 704.1}, {"capture_date": "2026-07-17", "model": "arpege", "x_ft": 155.5, "y_ft": 585.9}, {"capture_date": "2026-07-17", "model": "gem", "x_ft": 329.6, "y_ft": 701.6}], "13_dual_fast_3000": [{"capture_date": "2026-07-17", "model": "gfs", "x_ft": 537.2, "y_ft": 1512.2}, {"capture_date": "2026-07-17", "model": "hrrr", "x_ft": 340.6, "y_ft": 1461.7}, {"capture_date": "2026-07-17", "model": "ecmwf", "x_ft": 339.2, "y_ft": 1093.3}, {"capture_date": "2026-07-17", "model": "icon", "x_ft": 277.4, "y_ft": 1093.7}, {"capture_date": "2026-07-17", "model": "arpege", "x_ft": 307.7, "y_ft": 965.3}, {"capture_date": "2026-07-17", "model": "gem", "x_ft": 547.2, "y_ft": 1087.3}], "13_dual_fast_5000": [{"capture_date": "2026-07-17", "model": "gfs", "x_ft": 786.4, "y_ft": 2089.8}, {"capture_date": "2026-07-17", "model": "hrrr", "x_ft": 558.7, "y_ft": 1958.0}, {"capture_date": "2026-07-17", "model": "ecmwf", "x_ft": 553.7, "y_ft": 1581.2}, {"capture_date": "2026-07-17", "model": "icon", "x_ft": 462.0, "y_ft": 1506.7}, {"capture_date": "2026-07-17", "model": "arpege", "x_ft": 551.2, "y_ft": 1318.8}, {"capture_date": "2026-07-17", "model": "gem", "x_ft": 824.0, "y_ft": 1509.5}], "13_dual_fast_7000": [{"capture_date": "2026-07-17", "model": "gfs", "x_ft": 1036.5, "y_ft": 2667.7}, {"capture_date": "2026-07-17", "model": "hrrr", "x_ft": 825.8, "y_ft": 2410.5}, {"capture_date": "2026-07-17", "model": "ecmwf", "x_ft": 854.5, "y_ft": 2145.8}, {"capture_date": "2026-07-17", "model": "icon", "x_ft": 753.9, "y_ft": 1937.5}, {"capture_date": "2026-07-17", "model": "arpege", "x_ft": 878.4, "y_ft": 1649.1}, {"capture_date": "2026-07-17", "model": "gem", "x_ft": 1140.3, "y_ft": 1980.2}], "13_dual_fast_9000": [{"capture_date": "2026-07-17", "model": "gfs", "x_ft": 1215.7, "y_ft": 3267.9}, {"capture_date": "2026-07-17", "model": "hrrr", "x_ft": 1158.1, "y_ft": 2949.4}, {"capture_date": "2026-07-17", "model": "ecmwf", "x_ft": 1254.1, "y_ft": 2776.1}, {"capture_date": "2026-07-17", "model": "icon", "x_ft": 1196.4, "y_ft": 2491.5}, {"capture_date": "2026-07-17", "model": "arpege", "x_ft": 1342.5, "y_ft": 2287.8}, {"capture_date": "2026-07-17", "model": "gem", "x_ft": 1437.1, "y_ft": 2601.6}], "13_dual_slow_1000": [{"capture_date": "2026-07-17", "model": "gfs", "x_ft": 639.5, "y_ft": 1894.7}, {"capture_date": "2026-07-17", "model": "hrrr", "x_ft": 369.5, "y_ft": 1848.9}, {"capture_date": "2026-07-17", "model": "ecmwf", "x_ft": 386.8, "y_ft": 1356.1}, {"capture_date": "2026-07-17", "model": "icon", "x_ft": 331.4, "y_ft": 1381.8}, {"capture_date": "2026-07-17", "model": "arpege", "x_ft": 304.0, "y_ft": 1148.3}, {"capture_date": "2026-07-17", "model": "gem", "x_ft": 646.2, "y_ft": 1377.0}], "13_dual_slow_3000": [{"capture_date": "2026-07-17", "model": "gfs", "x_ft": 903.3, "y_ft": 2578.0}, {"capture_date": "2026-07-17", "model": "hrrr", "x_ft": 559.3, "y_ft": 2498.3}, {"capture_date": "2026-07-17", "model": "ecmwf", "x_ft": 564.0, "y_ft": 1858.7}, {"capture_date": "2026-07-17", "model": "icon", "x_ft": 466.9, "y_ft": 1868.8}, {"capture_date": "2026-07-17", "model": "arpege", "x_ft": 494.2, "y_ft": 1622.6}, {"capture_date": "2026-07-17", "model": "gem", "x_ft": 918.2, "y_ft": 1859.0}], "13_dual_slow_5000": [{"capture_date": "2026-07-17", "model": "gfs", "x_ft": 1214.7, "y_ft": 3299.9}, {"capture_date": "2026-07-17", "model": "hrrr", "x_ft": 831.9, "y_ft": 3118.7}, {"capture_date": "2026-07-17", "model": "ecmwf", "x_ft": 832.1, "y_ft": 2468.6}, {"capture_date": "2026-07-17", "model": "icon", "x_ft": 697.6, "y_ft": 2385.0}, {"capture_date": "2026-07-17", "model": "arpege", "x_ft": 798.6, "y_ft": 2064.5}, {"capture_date": "2026-07-17", "model": "gem", "x_ft": 1264.2, "y_ft": 2386.8}], "13_dual_slow_7000": [{"capture_date": "2026-07-17", "model": "gfs", "x_ft": 1527.5, "y_ft": 4022.2}, {"capture_date": "2026-07-17", "model": "hrrr", "x_ft": 1165.8, "y_ft": 3684.3}, {"capture_date": "2026-07-17", "model": "ecmwf", "x_ft": 1208.1, "y_ft": 3174.3}, {"capture_date": "2026-07-17", "model": "icon", "x_ft": 1062.5, "y_ft": 2923.5}, {"capture_date": "2026-07-17", "model": "arpege", "x_ft": 1207.6, "y_ft": 2477.4}, {"capture_date": "2026-07-17", "model": "gem", "x_ft": 1659.5, "y_ft": 2975.1}], "13_dual_slow_9000": [{"capture_date": "2026-07-17", "model": "gfs", "x_ft": 1751.4, "y_ft": 4772.6}, {"capture_date": "2026-07-17", "model": "hrrr", "x_ft": 1581.1, "y_ft": 4357.9}, {"capture_date": "2026-07-17", "model": "ecmwf", "x_ft": 1707.6, "y_ft": 3962.2}, {"capture_date": "2026-07-17", "model": "icon", "x_ft": 1615.6, "y_ft": 3616.1}, {"capture_date": "2026-07-17", "model": "arpege", "x_ft": 1787.6, "y_ft": 3275.8}, {"capture_date": "2026-07-17", "model": "gem", "x_ft": 2030.6, "y_ft": 3752.0}], "13_single_10fps_1000": [{"capture_date": "2026-07-17", "model": "gfs", "x_ft": 789.6, "y_ft": 2321.1}, {"capture_date": "2026-07-17", "model": "hrrr", "x_ft": 463.1, "y_ft": 2261.8}, {"capture_date": "2026-07-17", "model": "ecmwf", "x_ft": 480.6, "y_ft": 1663.9}, {"capture_date": "2026-07-17", "model": "icon", "x_ft": 408.5, "y_ft": 1690.0}, {"capture_date": "2026-07-17", "model": "arpege", "x_ft": 386.6, "y_ft": 1421.7}, {"capture_date": "2026-07-17", "model": "gem", "x_ft": 798.7, "y_ft": 1683.9}], "13_single_10fps_3000": [{"capture_date": "2026-07-17", "model": "gfs", "x_ft": 2899.5, "y_ft": 7787.3}, {"capture_date": "2026-07-17", "model": "hrrr", "x_ft": 1981.7, "y_ft": 7457.2}, {"capture_date": "2026-07-17", "model": "ecmwf", "x_ft": 1898.1, "y_ft": 5684.6}, {"capture_date": "2026-07-17", "model": "icon", "x_ft": 1492.1, "y_ft": 5586.4}, {"capture_date": "2026-07-17", "model": "arpege", "x_ft": 1908.6, "y_ft": 5215.8}, {"capture_date": "2026-07-17", "model": "gem", "x_ft": 2974.7, "y_ft": 5540.5}], "13_single_10fps_5000": [{"capture_date": "2026-07-17", "model": "gfs", "x_ft": 5391.1, "y_ft": 13562.8}, {"capture_date": "2026-07-17", "model": "hrrr", "x_ft": 4162.8, "y_ft": 12420.6}, {"capture_date": "2026-07-17", "model": "ecmwf", "x_ft": 4043.2, "y_ft": 10563.9}, {"capture_date": "2026-07-17", "model": "icon", "x_ft": 3338.1, "y_ft": 9715.8}, {"capture_date": "2026-07-17", "model": "arpege", "x_ft": 4343.3, "y_ft": 8751.0}, {"capture_date": "2026-07-17", "model": "gem", "x_ft": 5742.7, "y_ft": 9762.4}], "13_single_10fps_7000": [{"capture_date": "2026-07-17", "model": "gfs", "x_ft": 7892.8, "y_ft": 19341.3}, {"capture_date": "2026-07-17", "model": "hrrr", "x_ft": 6834.1, "y_ft": 16945.6}, {"capture_date": "2026-07-17", "model": "ecmwf", "x_ft": 7051.3, "y_ft": 16209.1}, {"capture_date": "2026-07-17", "model": "icon", "x_ft": 6257.5, "y_ft": 14023.7}, {"capture_date": "2026-07-17", "model": "arpege", "x_ft": 7615.2, "y_ft": 12054.1}, {"capture_date": "2026-07-17", "model": "gem", "x_ft": 8905.2, "y_ft": 14469.4}], "13_single_10fps_9000": [{"capture_date": "2026-07-17", "model": "gfs", "x_ft": 9684.1, "y_ft": 25344.2}, {"capture_date": "2026-07-17", "model": "hrrr", "x_ft": 10156.2, "y_ft": 22334.3}, {"capture_date": "2026-07-17", "model": "ecmwf", "x_ft": 11047.3, "y_ft": 22512.6}, {"capture_date": "2026-07-17", "model": "icon", "x_ft": 10682.5, "y_ft": 19564.5}, {"capture_date": "2026-07-17", "model": "arpege", "x_ft": 12255.9, "y_ft": 18441.1}, {"capture_date": "2026-07-17", "model": "gem", "x_ft": 11873.9, "y_ft": 20683.9}], "13_single_20fps_1000": [{"capture_date": "2026-07-17", "model": "gfs", "x_ft": 394.8, "y_ft": 1160.5}, {"capture_date": "2026-07-17", "model": "hrrr", "x_ft": 231.5, "y_ft": 1130.9}, {"capture_date": "2026-07-17", "model": "ecmwf", "x_ft": 240.3, "y_ft": 832.0}, {"capture_date": "2026-07-17", "model": "icon", "x_ft": 204.2, "y_ft": 845.0}, {"capture_date": "2026-07-17", "model": "arpege", "x_ft": 193.3, "y_ft": 710.8}, {"capture_date": "2026-07-17", "model": "gem", "x_ft": 399.4, "y_ft": 842.0}], "13_single_20fps_3000": [{"capture_date": "2026-07-17", "model": "gfs", "x_ft": 1449.7, "y_ft": 3893.6}, {"capture_date": "2026-07-17", "model": "hrrr", "x_ft": 990.8, "y_ft": 3728.6}, {"capture_date": "2026-07-17", "model": "ecmwf", "x_ft": 949.1, "y_ft": 2842.3}, {"capture_date": "2026-07-17", "model": "icon", "x_ft": 746.1, "y_ft": 2793.2}, {"capture_date": "2026-07-17", "model": "arpege", "x_ft": 954.3, "y_ft": 2607.9}, {"capture_date": "2026-07-17", "model": "gem", "x_ft": 1487.3, "y_ft": 2770.2}], "13_single_20fps_5000": [{"capture_date": "2026-07-17", "model": "gfs", "x_ft": 2695.5, "y_ft": 6781.4}, {"capture_date": "2026-07-17", "model": "hrrr", "x_ft": 2081.4, "y_ft": 6210.3}, {"capture_date": "2026-07-17", "model": "ecmwf", "x_ft": 2021.6, "y_ft": 5281.9}, {"capture_date": "2026-07-17", "model": "icon", "x_ft": 1669.0, "y_ft": 4857.9}, {"capture_date": "2026-07-17", "model": "arpege", "x_ft": 2171.7, "y_ft": 4375.5}, {"capture_date": "2026-07-17", "model": "gem", "x_ft": 2871.3, "y_ft": 4881.2}], "13_single_20fps_7000": [{"capture_date": "2026-07-17", "model": "gfs", "x_ft": 3946.4, "y_ft": 9670.7}, {"capture_date": "2026-07-17", "model": "hrrr", "x_ft": 3417.0, "y_ft": 8472.8}, {"capture_date": "2026-07-17", "model": "ecmwf", "x_ft": 3525.6, "y_ft": 8104.6}, {"capture_date": "2026-07-17", "model": "icon", "x_ft": 3128.7, "y_ft": 7011.8}, {"capture_date": "2026-07-17", "model": "arpege", "x_ft": 3807.6, "y_ft": 6027.0}, {"capture_date": "2026-07-17", "model": "gem", "x_ft": 4452.6, "y_ft": 7234.7}], "13_single_20fps_9000": [{"capture_date": "2026-07-17", "model": "gfs", "x_ft": 4842.0, "y_ft": 12672.1}, {"capture_date": "2026-07-17", "model": "hrrr", "x_ft": 5078.1, "y_ft": 11167.2}, {"capture_date": "2026-07-17", "model": "ecmwf", "x_ft": 5523.6, "y_ft": 11256.3}, {"capture_date": "2026-07-17", "model": "icon", "x_ft": 5341.2, "y_ft": 9782.3}, {"capture_date": "2026-07-17", "model": "arpege", "x_ft": 6128.0, "y_ft": 9220.5}, {"capture_date": "2026-07-17", "model": "gem", "x_ft": 5937.0, "y_ft": 10341.9}], "15_dual_fast_1000": [{"capture_date": "2026-07-17", "model": "gfs", "x_ft": 247.1, "y_ft": 1016.4}, {"capture_date": "2026-07-17", "model": "hrrr", "x_ft": 58.7, "y_ft": 917.2}, {"capture_date": "2026-07-17", "model": "ecmwf", "x_ft": 76.4, "y_ft": 708.9}, {"capture_date": "2026-07-17", "model": "icon", "x_ft": 47.1, "y_ft": 769.8}, {"capture_date": "2026-07-17", "model": "arpege", "x_ft": -42.5, "y_ft": 562.9}, {"capture_date": "2026-07-17", "model": "gem", "x_ft": 173.0, "y_ft": 935.2}], "15_dual_fast_3000": [{"capture_date": "2026-07-17", "model": "gfs", "x_ft": 410.2, "y_ft": 1585.0}, {"capture_date": "2026-07-17", "model": "hrrr", "x_ft": 113.3, "y_ft": 1417.6}, {"capture_date": "2026-07-17", "model": "ecmwf", "x_ft": 174.5, "y_ft": 1099.0}, {"capture_date": "2026-07-17", "model": "icon", "x_ft": 89.5, "y_ft": 1201.2}, {"capture_date": "2026-07-17", "model": "arpege", "x_ft": -29.8, "y_ft": 924.5}, {"capture_date": "2026-07-17", "model": "gem", "x_ft": 310.1, "y_ft": 1415.7}], "15_dual_fast_5000": [{"capture_date": "2026-07-17", "model": "gfs", "x_ft": 574.1, "y_ft": 2187.2}, {"capture_date": "2026-07-17", "model": "hrrr", "x_ft": 230.1, "y_ft": 1932.4}, {"capture_date": "2026-07-17", "model": "ecmwf", "x_ft": 371.0, "y_ft": 1539.2}, {"capture_date": "2026-07-17", "model": "icon", "x_ft": 225.9, "y_ft": 1654.6}, {"capture_date": "2026-07-17", "model": "arpege", "x_ft": 67.6, "y_ft": 1360.1}, {"capture_date": "2026-07-17", "model": "gem", "x_ft": 492.3, "y_ft": 1910.2}], "15_dual_fast_7000": [{"capture_date": "2026-07-17", "model": "gfs", "x_ft": 719.0, "y_ft": 2785.2}, {"capture_date": "2026-07-17", "model": "hrrr", "x_ft": 443.2, "y_ft": 2421.2}, {"capture_date": "2026-07-17", "model": "ecmwf", "x_ft": 685.3, "y_ft": 2005.2}, {"capture_date": "2026-07-17", "model": "icon", "x_ft": 491.5, "y_ft": 2092.8}, {"capture_date": "2026-07-17", "model": "arpege", "x_ft": 294.0, "y_ft": 1838.2}, {"capture_date": "2026-07-17", "model": "gem", "x_ft": 718.8, "y_ft": 2404.6}], "15_dual_fast_9000": [{"capture_date": "2026-07-17", "model": "gfs", "x_ft": 882.4, "y_ft": 3371.2}, {"capture_date": "2026-07-17", "model": "hrrr", "x_ft": 840.6, "y_ft": 2841.8}, {"capture_date": "2026-07-17", "model": "ecmwf", "x_ft": 1130.7, "y_ft": 2467.4}, {"capture_date": "2026-07-17", "model": "icon", "x_ft": 908.9, "y_ft": 2549.5}, {"capture_date": "2026-07-17", "model": "arpege", "x_ft": 721.5, "y_ft": 2347.0}, {"capture_date": "2026-07-17", "model": "gem", "x_ft": 1039.8, "y_ft": 2891.9}], "15_dual_slow_1000": [{"capture_date": "2026-07-17", "model": "gfs", "x_ft": 484.4, "y_ft": 1994.5}, {"capture_date": "2026-07-17", "model": "hrrr", "x_ft": 114.8, "y_ft": 1800.1}, {"capture_date": "2026-07-17", "model": "ecmwf", "x_ft": 148.7, "y_ft": 1391.3}, {"capture_date": "2026-07-17", "model": "icon", "x_ft": 92.1, "y_ft": 1510.6}, {"capture_date": "2026-07-17", "model": "arpege", "x_ft": -84.0, "y_ft": 1103.5}, {"capture_date": "2026-07-17", "model": "gem", "x_ft": 338.7, "y_ft": 1836.0}], "15_dual_slow_3000": [{"capture_date": "2026-07-17", "model": "gfs", "x_ft": 688.3, "y_ft": 2705.3}, {"capture_date": "2026-07-17", "model": "hrrr", "x_ft": 183.1, "y_ft": 2425.6}, {"capture_date": "2026-07-17", "model": "ecmwf", "x_ft": 271.4, "y_ft": 1878.8}, {"capture_date": "2026-07-17", "model": "icon", "x_ft": 145.2, "y_ft": 2049.8}, {"capture_date": "2026-07-17", "model": "arpege", "x_ft": -68.2, "y_ft": 1555.5}, {"capture_date": "2026-07-17", "model": "gem", "x_ft": 510.0, "y_ft": 2436.7}], "15_dual_slow_5000": [{"capture_date": "2026-07-17", "model": "gfs", "x_ft": 893.1, "y_ft": 3458.0}, {"capture_date": "2026-07-17", "model": "hrrr", "x_ft": 329.0, "y_ft": 3069.1}, {"capture_date": "2026-07-17", "model": "ecmwf", "x_ft": 517.1, "y_ft": 2429.1}, {"capture_date": "2026-07-17", "model": "icon", "x_ft": 315.6, "y_ft": 2616.6}, {"capture_date": "2026-07-17", "model": "arpege", "x_ft": 53.7, "y_ft": 2100.1}, {"capture_date": "2026-07-17", "model": "gem", "x_ft": 737.8, "y_ft": 3054.8}], "15_dual_slow_7000": [{"capture_date": "2026-07-17", "model": "gfs", "x_ft": 1074.3, "y_ft": 4205.5}, {"capture_date": "2026-07-17", "model": "hrrr", "x_ft": 595.3, "y_ft": 3680.1}, {"capture_date": "2026-07-17", "model": "ecmwf", "x_ft": 909.9, "y_ft": 3011.5}, {"capture_date": "2026-07-17", "model": "icon", "x_ft": 647.7, "y_ft": 3164.3}, {"capture_date": "2026-07-17", "model": "arpege", "x_ft": 336.6, "y_ft": 2697.7}, {"capture_date": "2026-07-17", "model": "gem", "x_ft": 1020.9, "y_ft": 3672.9}], "15_dual_slow_9000": [{"capture_date": "2026-07-17", "model": "gfs", "x_ft": 1278.5, "y_ft": 4938.1}, {"capture_date": "2026-07-17", "model": "hrrr", "x_ft": 1092.2, "y_ft": 4205.9}, {"capture_date": "2026-07-17", "model": "ecmwf", "x_ft": 1466.7, "y_ft": 3589.3}, {"capture_date": "2026-07-17", "model": "icon", "x_ft": 1169.4, "y_ft": 3735.2}, {"capture_date": "2026-07-17", "model": "arpege", "x_ft": 871.0, "y_ft": 3333.7}, {"capture_date": "2026-07-17", "model": "gem", "x_ft": 1422.2, "y_ft": 4281.9}], "15_single_10fps_1000": [{"capture_date": "2026-07-17", "model": "gfs", "x_ft": 599.0, "y_ft": 2441.3}, {"capture_date": "2026-07-17", "model": "hrrr", "x_ft": 145.4, "y_ft": 2199.8}, {"capture_date": "2026-07-17", "model": "ecmwf", "x_ft": 195.0, "y_ft": 1701.7}, {"capture_date": "2026-07-17", "model": "icon", "x_ft": 116.0, "y_ft": 1849.0}, {"capture_date": "2026-07-17", "model": "arpege", "x_ft": -95.5, "y_ft": 1363.4}, {"capture_date": "2026-07-17", "model": "gem", "x_ft": 424.6, "y_ft": 2235.9}], "15_single_10fps_3000": [{"capture_date": "2026-07-17", "model": "gfs", "x_ft": 2230.1, "y_ft": 8127.3}, {"capture_date": "2026-07-17", "model": "hrrr", "x_ft": 691.7, "y_ft": 7204.0}, {"capture_date": "2026-07-17", "model": "ecmwf", "x_ft": 1176.5, "y_ft": 5601.9}, {"capture_date": "2026-07-17", "model": "icon", "x_ft": 540.8, "y_ft": 6162.9}, {"capture_date": "2026-07-17", "model": "arpege", "x_ft": 31.0, "y_ft": 4979.6}, {"capture_date": "2026-07-17", "model": "gem", "x_ft": 1794.9, "y_ft": 7041.4}], "15_single_10fps_5000": [{"capture_date": "2026-07-17", "model": "gfs", "x_ft": 3868.7, "y_ft": 14149.2}, {"capture_date": "2026-07-17", "model": "hrrr", "x_ft": 1859.5, "y_ft": 12351.9}, {"capture_date": "2026-07-17", "model": "ecmwf", "x_ft": 3141.7, "y_ft": 10004.2}, {"capture_date": "2026-07-17", "model": "icon", "x_ft": 1904.4, "y_ft": 10697.3}, {"capture_date": "2026-07-17", "model": "arpege", "x_ft": 1005.7, "y_ft": 9336.1}, {"capture_date": "2026-07-17", "model": "gem", "x_ft": 3617.1, "y_ft": 11986.0}], "15_single_10fps_7000": [{"capture_date": "2026-07-17", "model": "gfs", "x_ft": 5318.3, "y_ft": 20129.2}, {"capture_date": "2026-07-17", "model": "hrrr", "x_ft": 3989.9, "y_ft": 17240.1}, {"capture_date": "2026-07-17", "model": "ecmwf", "x_ft": 6284.1, "y_ft": 14663.8}, {"capture_date": "2026-07-17", "model": "icon", "x_ft": 4560.9, "y_ft": 15079.2}, {"capture_date": "2026-07-17", "model": "arpege", "x_ft": 3268.9, "y_ft": 14116.9}, {"capture_date": "2026-07-17", "model": "gem", "x_ft": 5881.9, "y_ft": 16930.6}], "15_single_10fps_9000": [{"capture_date": "2026-07-17", "model": "gfs", "x_ft": 6952.3, "y_ft": 25989.6}, {"capture_date": "2026-07-17", "model": "hrrr", "x_ft": 7964.6, "y_ft": 21446.3}, {"capture_date": "2026-07-17", "model": "ecmwf", "x_ft": 10738.6, "y_ft": 19286.2}, {"capture_date": "2026-07-17", "model": "icon", "x_ft": 8734.7, "y_ft": 19646.1}, {"capture_date": "2026-07-17", "model": "arpege", "x_ft": 7544.3, "y_ft": 19204.9}, {"capture_date": "2026-07-17", "model": "gem", "x_ft": 9092.2, "y_ft": 21803.1}], "15_single_20fps_1000": [{"capture_date": "2026-07-17", "model": "gfs", "x_ft": 299.5, "y_ft": 1220.7}, {"capture_date": "2026-07-17", "model": "hrrr", "x_ft": 72.7, "y_ft": 1099.9}, {"capture_date": "2026-07-17", "model": "ecmwf", "x_ft": 97.5, "y_ft": 850.8}, {"capture_date": "2026-07-17", "model": "icon", "x_ft": 58.0, "y_ft": 924.5}, {"capture_date": "2026-07-17", "model": "arpege", "x_ft": -47.7, "y_ft": 681.7}, {"capture_date": "2026-07-17", "model": "gem", "x_ft": 212.3, "y_ft": 1118.0}], "15_single_20fps_3000": [{"capture_date": "2026-07-17", "model": "gfs", "x_ft": 1115.0, "y_ft": 4063.7}, {"capture_date": "2026-07-17", "model": "hrrr", "x_ft": 345.8, "y_ft": 3602.0}, {"capture_date": "2026-07-17", "model": "ecmwf", "x_ft": 588.2, "y_ft": 2801.0}, {"capture_date": "2026-07-17", "model": "icon", "x_ft": 270.4, "y_ft": 3081.5}, {"capture_date": "2026-07-17", "model": "arpege", "x_ft": 15.5, "y_ft": 2489.8}, {"capture_date": "2026-07-17", "model": "gem", "x_ft": 897.4, "y_ft": 3520.7}], "15_single_20fps_5000": [{"capture_date": "2026-07-17", "model": "gfs", "x_ft": 1934.4, "y_ft": 7074.6}, {"capture_date": "2026-07-17", "model": "hrrr", "x_ft": 929.7, "y_ft": 6175.9}, {"capture_date": "2026-07-17", "model": "ecmwf", "x_ft": 1570.8, "y_ft": 5002.1}, {"capture_date": "2026-07-17", "model": "icon", "x_ft": 952.2, "y_ft": 5348.7}, {"capture_date": "2026-07-17", "model": "arpege", "x_ft": 502.8, "y_ft": 4668.0}, {"capture_date": "2026-07-17", "model": "gem", "x_ft": 1808.6, "y_ft": 5993.0}], "15_single_20fps_7000": [{"capture_date": "2026-07-17", "model": "gfs", "x_ft": 2659.2, "y_ft": 10064.6}, {"capture_date": "2026-07-17", "model": "hrrr", "x_ft": 1995.0, "y_ft": 8620.0}, {"capture_date": "2026-07-17", "model": "ecmwf", "x_ft": 3142.1, "y_ft": 7331.9}, {"capture_date": "2026-07-17", "model": "icon", "x_ft": 2280.5, "y_ft": 7539.6}, {"capture_date": "2026-07-17", "model": "arpege", "x_ft": 1634.4, "y_ft": 7058.4}, {"capture_date": "2026-07-17", "model": "gem", "x_ft": 2941.0, "y_ft": 8465.3}], "15_single_20fps_9000": [{"capture_date": "2026-07-17", "model": "gfs", "x_ft": 3476.1, "y_ft": 12994.8}, {"capture_date": "2026-07-17", "model": "hrrr", "x_ft": 3982.3, "y_ft": 10723.2}, {"capture_date": "2026-07-17", "model": "ecmwf", "x_ft": 5369.3, "y_ft": 9643.1}, {"capture_date": "2026-07-17", "model": "icon", "x_ft": 4367.4, "y_ft": 9823.0}, {"capture_date": "2026-07-17", "model": "arpege", "x_ft": 3772.2, "y_ft": 9602.5}, {"capture_date": "2026-07-17", "model": "gem", "x_ft": 4546.1, "y_ft": 10901.5}]}, "actuals": {}}